{"1944":{"time":-790189200,"summary":"Clear throughout the day.","icon":"clear-day","sunriseTime":-790158894,"sunsetTime":-790124788,"moonPhase":0.09,"precipType":"rain","temperatureHigh":60.76,"temperatureHighTime":-790138800,"temperatureLow":50.46,"temperatureLowTime":-790074000,"apparentTemperatureHigh":60.76,"apparentTemperatureHighTime":-790138800,"apparentTemperatureLow":50.46,"apparentTemperatureLowTime":-790074000,"dewPoint":43.67,"humidity":0.74,"pressure":1020.2,"windSpeed":8.2,"windBearing":89,"uvIndex":0,"uvIndexTime":-790189200,"temperatureMin":45.91,"temperatureMinTime":-790171200,"temperatureMax":60.76,"temperatureMaxTime":-790138800,"apparentTemperatureMin":41.01,"apparentTemperatureMinTime":-790164000,"apparentTemperatureMax":60.76,"apparentTemperatureMaxTime":-790138800},"1945":{"time":-758649600,"summary":"Clear throughout the day.","icon":"clear-day","sunriseTime":-758622903,"sunsetTime":-758588794,"moonPhase":0.47,"precipType":"rain","temperatureHigh":53.67,"temperatureHighTime":-758599200,"temperatureLow":32.65,"temperatureLowTime":-758538000,"apparentTemperatureHigh":53.67,"apparentTemperatureHighTime":-758599200,"apparentTemperatureLow":32.65,"apparentTemperatureLowTime":-758538000,"dewPoint":38.92,"humidity":0.92,"pressure":1022.64,"windSpeed":1.27,"windBearing":288,"uvIndex":0,"uvIndexTime":-758649600,"temperatureMin":32.34,"temperatureMinTime":-758635200,"temperatureMax":53.67,"temperatureMaxTime":-758599200,"apparentTemperatureMin":32.34,"apparentTemperatureMinTime":-758635200,"apparentTemperatureMax":53.67,"apparentTemperatureMaxTime":-758599200},"1946":{},"1947":{},"1948":{},"1949":{},"1950":{},"1951":{},"1952":{},"1953":{},"1954":{},"1955":{},"1956":{},"1957":{},"1958":{},"1959":{},"1960":{},"1961":{},"1962":{},"1963":{},"1964":{},"1965":{},"1966":{},"1967":{},"1968":{},"1969":{},"1970":{},"1971":{},"1972":{},"1973":{"time":124963200,"summary":"Mostly cloudy throughout the day.","icon":"partly-cloudy-day","sunriseTime":124989900,"sunsetTime":125024008,"moonPhase":0.8,"temperatureHigh":59,"temperatureHighTime":125010000,"temperatureLow":32.02,"temperatureLowTime":125078400,"apparentTemperatureHigh":59,"apparentTemperatureHighTime":125010000,"apparentTemperatureLow":24.85,"apparentTemperatureLowTime":125078400,"dewPoint":46.52,"humidity":0.87,"windSpeed":8.91,"windBearing":265,"cloudCover":0.49,"uvIndex":2,"uvIndexTime":125006400,"visibility":9.811,"temperatureMin":38.84,"temperatureMinTime":125046000,"temperatureMax":59,"temperatureMaxTime":125010000,"apparentTemperatureMin":33.15,"apparentTemperatureMinTime":125046000,"apparentTemperatureMax":59,"apparentTemperatureMaxTime":125010000},"1974":{"time":156499200,"summary":"Foggy in the morning.","icon":"partly-cloudy-day","sunriseTime":156525891,"sunsetTime":156560003,"moonPhase":0.14,"windSpeed":7.69,"windBearing":331,"cloudCover":0.34,"uvIndex":2,"uvIndexTime":156542400,"visibility":8.922},"1975":{"time":188035200,"summary":"Foggy until morning, starting again in the evening.","icon":"partly-cloudy-day","sunriseTime":188061882,"sunsetTime":188095998,"moonPhase":0.49,"temperatureHigh":57.92,"temperatureHighTime":188089200,"temperatureLow":31.11,"temperatureLowTime":188150400,"apparentTemperatureHigh":57.92,"apparentTemperatureHighTime":188089200,"apparentTemperatureLow":30.36,"apparentTemperatureLowTime":188118000,"dewPoint":38.07,"humidity":0.81,"windSpeed":2.08,"windBearing":20,"cloudCover":0.52,"uvIndex":2,"uvIndexTime":188078400,"visibility":3.567,"temperatureMin":33.07,"temperatureMinTime":188064000,"temperatureMax":57.92,"temperatureMaxTime":188089200,"apparentTemperatureMin":30.36,"apparentTemperatureMinTime":188118000,"apparentTemperatureMax":57.92,"apparentTemperatureMaxTime":188089200},"1976":{"time":219657600,"summary":"Foggy in the morning.","icon":"partly-cloudy-day","sunriseTime":219684309,"sunsetTime":219718413,"moonPhase":0.89,"temperatureHigh":62.06,"temperatureHighTime":219711600,"temperatureLow":30.18,"temperatureLowTime":219765600,"apparentTemperatureHigh":62.06,"apparentTemperatureHighTime":219711600,"apparentTemperatureLow":30.18,"apparentTemperatureLowTime":219765600,"dewPoint":32.66,"humidity":0.63,"windSpeed":3.06,"windBearing":108,"cloudCover":0.14,"uvIndex":2,"uvIndexTime":219700800,"visibility":3.633,"temperatureMin":29.1,"temperatureMinTime":219679200,"temperatureMax":62.06,"temperatureMaxTime":219711600,"apparentTemperatureMin":28.59,"apparentTemperatureMinTime":219682800,"apparentTemperatureMax":62.06,"apparentTemperatureMaxTime":219711600},"1977":{"time":251193600,"summary":"Mostly cloudy throughout the day.","icon":"partly-cloudy-day","sunriseTime":251220300,"sunsetTime":251254408,"moonPhase":0.28,"temperatureHigh":57.92,"temperatureHighTime":251218800,"temperatureLow":39.92,"temperatureLowTime":251301600,"apparentTemperatureHigh":57.92,"apparentTemperatureHighTime":251218800,"apparentTemperatureLow":39.92,"apparentTemperatureLowTime":251301600,"dewPoint":48.4,"humidity":0.82,"windSpeed":6.5,"windBearing":230,"cloudCover":0.63,"uvIndex":2,"uvIndexTime":251236800,"visibility":8.883,"temperatureMin":44.95,"temperatureMinTime":251272800,"temperatureMax":57.92,"temperatureMaxTime":251215200,"apparentTemperatureMin":44.95,"apparentTemperatureMinTime":251272800,"apparentTemperatureMax":57.92,"apparentTemperatureMaxTime":251215200},"1978":{"time":282729600,"summary":"Foggy in the afternoon.","icon":"cloudy","sunriseTime":282756291,"sunsetTime":282790403,"moonPhase":0.61,"temperatureHigh":49.99,"temperatureHighTime":282758400,"temperatureLow":39.01,"temperatureLowTime":282844800,"apparentTemperatureHigh":49.99,"apparentTemperatureHighTime":282776400,"apparentTemperatureLow":35.74,"apparentTemperatureLowTime":282844800,"dewPoint":44.75,"humidity":0.89,"windSpeed":4.11,"windBearing":152,"cloudCover":0.9,"uvIndex":2,"uvIndexTime":282772800,"visibility":6.647,"temperatureMin":44.06,"temperatureMinTime":282805200,"temperatureMax":49.99,"temperatureMaxTime":282758400,"apparentTemperatureMin":40.85,"apparentTemperatureMinTime":282805200,"apparentTemperatureMax":49.99,"apparentTemperatureMaxTime":282776400},"1979":{"time":314265600,"summary":"Foggy in the morning.","icon":"partly-cloudy-day","sunriseTime":314292282,"sunsetTime":314326398,"moonPhase":0.96,"temperatureHigh":57.92,"temperatureHighTime":314319600,"temperatureLow":33.07,"temperatureLowTime":314373600,"apparentTemperatureHigh":57.92,"apparentTemperatureHighTime":314319600,"apparentTemperatureLow":27.78,"apparentTemperatureLowTime":314377200,"dewPoint":40.87,"humidity":0.83,"windSpeed":3.63,"windBearing":96,"cloudCover":0.37,"uvIndex":2,"uvIndexTime":314308800,"visibility":5.434,"temperatureMin":31.11,"temperatureMinTime":314294400,"temperatureMax":57.92,"temperatureMaxTime":314319600,"apparentTemperatureMin":26.06,"apparentTemperatureMinTime":314290800,"apparentTemperatureMax":57.92,"apparentTemperatureMaxTime":314319600},"1980":{"time":345888000,"summary":"Mostly cloudy throughout the day.","icon":"partly-cloudy-day","sunriseTime":345914710,"sunsetTime":345948813,"moonPhase":0.37,"temperatureHigh":62.96,"temperatureHighTime":345942000,"temperatureLow":48.93,"temperatureLowTime":345996000,"apparentTemperatureHigh":62.96,"apparentTemperatureHighTime":345942000,"apparentTemperatureLow":48.93,"apparentTemperatureLowTime":345996000,"dewPoint":45.85,"humidity":0.85,"windSpeed":2.68,"windBearing":332,"cloudCover":0.81,"uvIndex":2,"uvIndexTime":345931200,"visibility":3.707,"temperatureMin":35.97,"temperatureMinTime":345916800,"temperatureMax":62.96,"temperatureMaxTime":345942000,"apparentTemperatureMin":32.04,"apparentTemperatureMinTime":345920400,"apparentTemperatureMax":62.96,"apparentTemperatureMaxTime":345942000},"1981":{"time":377424000,"summary":"Foggy in the morning and afternoon.","icon":"cloudy","sunriseTime":377450701,"sunsetTime":377484808,"moonPhase":0.75,"temperatureHigh":57.03,"temperatureHighTime":377478000,"apparentTemperatureHigh":57.03,"apparentTemperatureHighTime":377478000,"dewPoint":47.01,"humidity":0.91,"windSpeed":6.23,"windBearing":121,"cloudCover":0.89,"uvIndex":2,"uvIndexTime":377470800,"visibility":3.105,"temperatureMin":41,"temperatureMinTime":377452800,"temperatureMax":57.03,"temperatureMaxTime":377478000,"apparentTemperatureMin":37.22,"apparentTemperatureMinTime":377452800,"apparentTemperatureMax":57.03,"apparentTemperatureMaxTime":377478000},"1982":{"time":408960000,"summary":"Mostly cloudy throughout the day.","icon":"partly-cloudy-day","sunriseTime":408986692,"sunsetTime":409020803,"moonPhase":0.09,"temperatureHigh":59,"temperatureHighTime":409003200,"apparentTemperatureHigh":59,"apparentTemperatureHighTime":409003200,"dewPoint":47.12,"humidity":0.76,"windSpeed":5.09,"windBearing":237,"cloudCover":0.48,"uvIndex":2,"uvIndexTime":409003200,"visibility":10,"temperatureMin":46.94,"temperatureMinTime":409032000,"temperatureMax":59,"temperatureMaxTime":409003200,"apparentTemperatureMin":46.94,"apparentTemperatureMinTime":409032000,"apparentTemperatureMax":59,"apparentTemperatureMaxTime":409003200},"1983":{"time":440496000,"summary":"Foggy in the morning.","icon":"partly-cloudy-day","sunriseTime":440522683,"sunsetTime":440556798,"moonPhase":0.43,"temperatureHigh":60.09,"temperatureHighTime":440546400,"apparentTemperatureHigh":60.09,"apparentTemperatureHighTime":440546400,"dewPoint":50.94,"humidity":0.89,"windSpeed":3.12,"windBearing":314,"cloudCover":0.34,"uvIndex":2,"uvIndexTime":440539200,"visibility":9.312,"temperatureMin":48.02,"temperatureMinTime":440521200,"temperatureMax":60.09,"temperatureMaxTime":440546400,"apparentTemperatureMin":45.54,"apparentTemperatureMinTime":440568000,"apparentTemperatureMax":60.09,"apparentTemperatureMaxTime":440546400},"1984":{"time":472118400,"summary":"Partly cloudy throughout the day.","icon":"partly-cloudy-day","sunriseTime":472145110,"sunsetTime":472179214,"moonPhase":0.84,"temperatureHigh":53.06,"temperatureHighTime":472161600,"apparentTemperatureHigh":53.06,"apparentTemperatureHighTime":472161600,"dewPoint":37.05,"humidity":0.77,"windSpeed":9.2,"windBearing":65,"cloudCover":0.26,"uvIndex":2,"uvIndexTime":472161600,"visibility":10,"temperatureMin":32.02,"temperatureMinTime":472143600,"temperatureMax":53.06,"temperatureMaxTime":472161600,"apparentTemperatureMin":24.15,"apparentTemperatureMinTime":472143600,"apparentTemperatureMax":53.06,"apparentTemperatureMaxTime":472161600},"1985":{"time":503654400,"summary":"Foggy in the morning.","icon":"clear-day","sunriseTime":503681101,"sunsetTime":503715208,"moonPhase":0.22,"temperatureHigh":55.94,"temperatureHighTime":503712000,"apparentTemperatureHigh":55.94,"apparentTemperatureHighTime":503712000,"dewPoint":32.02,"humidity":0.64,"windSpeed":0,"uvIndex":1,"uvIndexTime":503704800,"visibility":3.464,"temperatureMin":30.18,"temperatureMinTime":503679600,"temperatureMax":55.94,"temperatureMaxTime":503712000,"apparentTemperatureMin":30.18,"apparentTemperatureMinTime":503679600,"apparentTemperatureMax":55.94,"apparentTemperatureMaxTime":503712000},"1986":{"time":535190400,"summary":"Foggy in the morning.","icon":"partly-cloudy-day","sunriseTime":535217092,"sunsetTime":535251203,"moonPhase":0.56,"temperatureHigh":62.96,"temperatureHighTime":535244400,"apparentTemperatureHigh":62.96,"apparentTemperatureHighTime":535244400,"dewPoint":45.65,"humidity":0.82,"windSpeed":4.74,"windBearing":105,"cloudCover":0.46,"uvIndex":2,"uvIndexTime":535233600,"visibility":6.205,"temperatureMin":33.98,"temperatureMinTime":535215600,"temperatureMax":62.96,"temperatureMaxTime":535244400,"apparentTemperatureMin":33.98,"apparentTemperatureMinTime":535215600,"apparentTemperatureMax":62.96,"apparentTemperatureMaxTime":535244400},"1987":{"time":566726400,"summary":"Mostly cloudy throughout the day.","icon":"partly-cloudy-day","sunriseTime":566753083,"sunsetTime":566787198,"moonPhase":0.9,"temperatureHigh":57.03,"temperatureHighTime":566780400,"apparentTemperatureHigh":57.03,"apparentTemperatureHighTime":566780400,"dewPoint":43.31,"humidity":0.81,"windSpeed":5.45,"windBearing":320,"cloudCover":0.26,"uvIndex":2,"uvIndexTime":566769600,"visibility":10,"temperatureMin":42.07,"temperatureMinTime":566751600,"temperatureMax":57.03,"temperatureMaxTime":566780400,"apparentTemperatureMin":38.33,"apparentTemperatureMinTime":566751600,"apparentTemperatureMax":57.03,"apparentTemperatureMaxTime":566780400},"1988":{"time":598348800,"summary":"Mostly cloudy throughout the day.","icon":"partly-cloudy-day","sunriseTime":598375510,"sunsetTime":598409614,"moonPhase":0.32,"temperatureHigh":55.04,"temperatureHighTime":598402800,"apparentTemperatureHigh":55.04,"apparentTemperatureHighTime":598402800,"dewPoint":36.71,"humidity":0.72,"windSpeed":0.82,"windBearing":180,"cloudCover":0.5,"uvIndex":2,"uvIndexTime":598395600,"visibility":9.999,"temperatureMin":31.11,"temperatureMinTime":598374000,"temperatureMax":55.04,"temperatureMaxTime":598402800,"apparentTemperatureMin":31.11,"apparentTemperatureMinTime":598374000,"apparentTemperatureMax":55.04,"apparentTemperatureMaxTime":598402800},"1989":{"time":629884800,"summary":"Foggy in the morning and afternoon.","icon":"cloudy","sunriseTime":629911501,"sunsetTime":629945609,"moonPhase":0.69,"temperatureHigh":46.05,"temperatureHighTime":629953200,"apparentTemperatureHigh":46.05,"apparentTemperatureHighTime":629953200,"dewPoint":41.52,"humidity":0.98,"windSpeed":0.5,"windBearing":281,"cloudCover":0.97,"uvIndex":2,"uvIndexTime":629928000,"visibility":2.841,"temperatureMin":37.04,"temperatureMinTime":629913600,"temperatureMax":46.05,"temperatureMaxTime":629953200,"apparentTemperatureMin":37.04,"apparentTemperatureMinTime":629913600,"apparentTemperatureMax":46.05,"apparentTemperatureMaxTime":629953200},"1990":{"time":661420800,"summary":"Partly cloudy throughout the day.","icon":"clear-day","sunriseTime":661447492,"sunsetTime":661481604,"moonPhase":0.03,"temperatureHigh":60.99,"temperatureHighTime":661474800,"apparentTemperatureHigh":60.99,"apparentTemperatureHighTime":661474800,"dewPoint":40.9,"humidity":0.81,"windSpeed":1.81,"windBearing":128,"cloudCover":0.09,"uvIndex":2,"uvIndexTime":661464000,"visibility":10,"temperatureMin":30.18,"temperatureMinTime":661446000,"temperatureMax":60.99,"temperatureMaxTime":661474800,"apparentTemperatureMin":30.18,"apparentTemperatureMinTime":661446000,"apparentTemperatureMax":60.99,"apparentTemperatureMaxTime":661474800},"1991":{"time":692956800,"summary":"Overcast throughout the day.","icon":"cloudy","sunriseTime":692983483,"sunsetTime":693017599,"moonPhase":0.38,"temperatureHigh":46.05,"temperatureHighTime":693010800,"apparentTemperatureHigh":46.05,"apparentTemperatureHighTime":693010800,"dewPoint":40.12,"humidity":0.93,"windSpeed":0.29,"windBearing":170,"cloudCover":0.95,"uvIndex":2,"uvIndexTime":693003600,"visibility":3.813,"temperatureMin":35.07,"temperatureMinTime":692985600,"temperatureMax":46.05,"temperatureMaxTime":693010800,"apparentTemperatureMin":35.07,"apparentTemperatureMinTime":692985600,"apparentTemperatureMax":46.05,"apparentTemperatureMaxTime":693010800},"1992":{"time":724579200,"summary":"Overcast throughout the day.","icon":"partly-cloudy-day","sunriseTime":724605911,"sunsetTime":724640014,"moonPhase":0.8,"temperatureHigh":49.99,"temperatureHighTime":724629600,"apparentTemperatureHigh":45.59,"apparentTemperatureHighTime":724629600,"dewPoint":38.99,"humidity":0.8,"windSpeed":7.45,"windBearing":282,"cloudCover":0.71,"uvIndex":2,"uvIndexTime":724622400,"visibility":9.799,"temperatureMin":37.93,"temperatureMinTime":724651200,"temperatureMax":49.99,"temperatureMaxTime":724629600,"apparentTemperatureMin":36.37,"apparentTemperatureMinTime":724640400,"apparentTemperatureMax":45.59,"apparentTemperatureMaxTime":724629600},"1993":{"time":756115200,"summary":"Foggy in the morning.","icon":"partly-cloudy-day","sunriseTime":756141902,"sunsetTime":756176009,"moonPhase":0.17,"temperatureHigh":49.99,"temperatureHighTime":756165600,"apparentTemperatureHigh":49.99,"apparentTemperatureHighTime":756165600,"dewPoint":36.28,"humidity":0.86,"windSpeed":0,"cloudCover":0.79,"uvIndex":2,"uvIndexTime":756158400,"visibility":8.225,"temperatureMin":30.95,"temperatureMinTime":756136800,"temperatureMax":49.99,"temperatureMaxTime":756165600,"apparentTemperatureMin":30.95,"apparentTemperatureMinTime":756136800,"apparentTemperatureMax":49.99,"apparentTemperatureMaxTime":756165600},"1994":{"time":787651200,"summary":"Foggy in the morning and afternoon.","icon":"cloudy","sunriseTime":787677893,"sunsetTime":787712004,"moonPhase":0.5,"temperatureHigh":47.83,"temperatureHighTime":787705200,"temperatureLow":43.89,"temperatureLowTime":787762800,"apparentTemperatureHigh":47.83,"apparentTemperatureHighTime":787705200,"apparentTemperatureLow":43.61,"apparentTemperatureLowTime":787755600,"dewPoint":43.41,"humidity":0.93,"windSpeed":0.34,"windBearing":311,"cloudCover":1,"uvIndex":2,"uvIndexTime":787694400,"visibility":2.345,"temperatureMin":41.92,"temperatureMinTime":787683600,"temperatureMax":47.83,"temperatureMaxTime":787705200,"apparentTemperatureMin":40.36,"apparentTemperatureMinTime":787669200,"apparentTemperatureMax":47.83,"apparentTemperatureMaxTime":787705200},"1995":{"time":819187200,"summary":"Mostly cloudy throughout the day.","icon":"partly-cloudy-day","sunriseTime":819213884,"sunsetTime":819247999,"moonPhase":0.85,"temperatureHigh":57.92,"temperatureHighTime":819241200,"apparentTemperatureHigh":57.92,"apparentTemperatureHighTime":819241200,"dewPoint":40.14,"humidity":0.75,"windSpeed":2.86,"windBearing":129,"cloudCover":0.67,"uvIndex":2,"uvIndexTime":819234000,"visibility":10,"temperatureMin":34.87,"temperatureMinTime":819216000,"temperatureMax":57.92,"temperatureMaxTime":819241200,"apparentTemperatureMin":34.87,"apparentTemperatureMinTime":819216000,"apparentTemperatureMax":57.92,"apparentTemperatureMaxTime":819241200},"1996":{"time":850809600,"summary":"Windy in the afternoon.","icon":"partly-cloudy-day","sunriseTime":850836311,"sunsetTime":850870414,"moonPhase":0.28,"temperatureHigh":71.61,"temperatureHighTime":850863600,"apparentTemperatureHigh":71.61,"apparentTemperatureHighTime":850863600,"dewPoint":24.94,"humidity":0.35,"windSpeed":15.28,"windBearing":357,"cloudCover":0.49,"uvIndex":2,"uvIndexTime":850852800,"visibility":10,"temperatureMin":37.4,"temperatureMinTime":850834800,"temperatureMax":71.61,"temperatureMaxTime":850863600,"apparentTemperatureMin":37.4,"apparentTemperatureMinTime":850834800,"apparentTemperatureMax":71.61,"apparentTemperatureMaxTime":850863600},"1997":{"time":882345600,"summary":"Foggy in the morning and afternoon.","icon":"cloudy","sunriseTime":882372302,"sunsetTime":882406409,"moonPhase":0.64,"temperatureHigh":53.6,"temperatureHighTime":882396000,"apparentTemperatureHigh":53.6,"apparentTemperatureHighTime":882396000,"dewPoint":48.34,"humidity":0.92,"windSpeed":4.16,"windBearing":343,"cloudCover":1,"uvIndex":2,"uvIndexTime":882388800,"visibility":5.653,"temperatureMin":48.21,"temperatureMinTime":882370800,"temperatureMax":53.6,"temperatureMaxTime":882396000,"apparentTemperatureMin":46.3,"apparentTemperatureMinTime":882385200,"apparentTemperatureMax":53.6,"apparentTemperatureMaxTime":882396000},"1998":{"time":913881600,"summary":"Foggy until morning, starting again in the evening.","icon":"partly-cloudy-day","sunriseTime":913908293,"sunsetTime":913942404,"moonPhase":0.98,"precipType":"rain","temperatureHigh":66.21,"temperatureHighTime":913935600,"temperatureLow":33.78,"temperatureLowTime":913996800,"apparentTemperatureHigh":66.21,"apparentTemperatureHighTime":913935600,"apparentTemperatureLow":32.79,"apparentTemperatureLowTime":913982400,"dewPoint":42.57,"humidity":0.83,"pressure":1018.61,"windSpeed":1.3,"windBearing":330,"cloudCover":0.17,"uvIndex":2,"uvIndexTime":913924800,"visibility":5.592,"temperatureMin":35.6,"temperatureMinTime":913903200,"temperatureMax":66.21,"temperatureMaxTime":913935600,"apparentTemperatureMin":35.6,"apparentTemperatureMinTime":913903200,"apparentTemperatureMax":66.21,"apparentTemperatureMaxTime":913935600},"1999":{"time":945417600,"summary":"Foggy in the morning and overnight.","icon":"partly-cloudy-day","sunriseTime":945444284,"sunsetTime":945478399,"moonPhase":0.33,"precipType":"rain","temperatureHigh":64.4,"temperatureHighTime":945471600,"temperatureLow":35.6,"temperatureLowTime":945518400,"apparentTemperatureHigh":64.4,"apparentTemperatureHighTime":945471600,"apparentTemperatureLow":31.57,"apparentTemperatureLowTime":945525600,"dewPoint":41.3,"humidity":0.86,"pressure":1023.42,"windSpeed":1.09,"windBearing":169,"cloudCover":0.35,"uvIndex":2,"uvIndexTime":945464400,"visibility":5.717,"temperatureMin":33.78,"temperatureMinTime":945435600,"temperatureMax":64.4,"temperatureMaxTime":945471600,"apparentTemperatureMin":30.87,"apparentTemperatureMinTime":945442800,"apparentTemperatureMax":64.4,"apparentTemperatureMaxTime":945471600},"2000":{"time":977040000,"summary":"Foggy in the morning.","icon":"clear-day","sunriseTime":977066712,"sunsetTime":977100815,"moonPhase":0.76,"precipType":"rain","temperatureHigh":65.99,"temperatureHighTime":977086800,"temperatureLow":28.02,"temperatureLowTime":977155200,"apparentTemperatureHigh":65.99,"apparentTemperatureHighTime":977086800,"apparentTemperatureLow":22.72,"apparentTemperatureLowTime":977155200,"dewPoint":29.78,"humidity":0.67,"pressure":1026.5,"windSpeed":6.29,"windBearing":4,"cloudCover":0.11,"uvIndex":2,"uvIndexTime":977083200,"visibility":8.285,"temperatureMin":31.99,"temperatureMinTime":977065200,"temperatureMax":65.99,"temperatureMaxTime":977086800,"apparentTemperatureMin":25.53,"apparentTemperatureMinTime":977065200,"apparentTemperatureMax":65.99,"apparentTemperatureMaxTime":977086800},"2001":{"time":1008576000,"summary":"Rain in the morning.","icon":"partly-cloudy-day","sunriseTime":1008602703,"sunsetTime":1008636809,"moonPhase":0.11,"temperatureHigh":58.96,"temperatureHighTime":1008626400,"temperatureLow":35.03,"temperatureLowTime":1008687600,"apparentTemperatureHigh":58.96,"apparentTemperatureHighTime":1008626400,"apparentTemperatureLow":35.03,"apparentTemperatureLowTime":1008687600,"dewPoint":47.91,"humidity":0.88,"pressure":1021.9,"windSpeed":3.55,"windBearing":156,"cloudCover":0.8,"uvIndex":2,"uvIndexTime":1008619200,"visibility":7.529,"temperatureMin":42.94,"temperatureMinTime":1008658800,"temperatureMax":58.96,"temperatureMaxTime":1008626400,"apparentTemperatureMin":41.32,"apparentTemperatureMinTime":1008658800,"apparentTemperatureMax":58.96,"apparentTemperatureMaxTime":1008626400},"2002":{"time":1040112000,"summary":"Light rain throughout the day.","icon":"rain","sunriseTime":1040138694,"sunsetTime":1040172804,"moonPhase":0.45,"precipIntensity":0.01,"precipIntensityMax":0.0201,"precipIntensityMaxTime":1040126400,"precipProbability":1,"precipType":"rain","temperatureHigh":52.79,"temperatureHighTime":1040162400,"temperatureLow":37.92,"temperatureLowTime":1040223600,"apparentTemperatureHigh":52.79,"apparentTemperatureHighTime":1040162400,"apparentTemperatureLow":37.92,"apparentTemperatureLowTime":1040223600,"dewPoint":41.39,"humidity":0.82,"pressure":1009.77,"windSpeed":3.11,"windGust":13.55,"windGustTime":1040173200,"windBearing":290,"cloudCover":0.54,"uvIndex":2,"uvIndexTime":1040158800,"visibility":7.259,"temperatureMin":41.53,"temperatureMinTime":1040194800,"temperatureMax":52.79,"temperatureMaxTime":1040162400,"apparentTemperatureMin":41.53,"apparentTemperatureMinTime":1040194800,"apparentTemperatureMax":52.79,"apparentTemperatureMaxTime":1040162400},"2003":{"time":1071648000,"summary":"Foggy in the morning and overnight.","icon":"clear-day","sunriseTime":1071674685,"sunsetTime":1071708799,"moonPhase":0.8,"precipIntensity":0,"precipIntensityMax":0,"precipProbability":0,"temperatureHigh":58.26,"temperatureHighTime":1071702000,"temperatureLow":35.61,"temperatureLowTime":1071756000,"apparentTemperatureHigh":58.26,"apparentTemperatureHighTime":1071702000,"apparentTemperatureLow":35.61,"apparentTemperatureLowTime":1071756000,"dewPoint":36.61,"humidity":0.74,"pressure":1023.07,"windSpeed":1.08,"windGust":6.38,"windGustTime":1071694800,"windBearing":106,"cloudCover":0.08,"uvIndex":2,"uvIndexTime":1071691200,"visibility":8.123,"temperatureMin":35.03,"temperatureMinTime":1071673200,"temperatureMax":58.26,"temperatureMaxTime":1071702000,"apparentTemperatureMin":35.03,"apparentTemperatureMinTime":1071673200,"apparentTemperatureMax":58.26,"apparentTemperatureMaxTime":1071702000},"2004":{"time":1103270400,"summary":"Foggy until morning, starting again in the evening.","icon":"partly-cloudy-day","sunriseTime":1103297112,"sunsetTime":1103331215,"moonPhase":0.23,"precipIntensity":0,"precipIntensityMax":0,"precipProbability":0,"temperatureHigh":63.55,"temperatureHighTime":1103324400,"temperatureLow":38.97,"temperatureLowTime":1103382000,"apparentTemperatureHigh":63.55,"apparentTemperatureHighTime":1103324400,"apparentTemperatureLow":38.97,"apparentTemperatureLowTime":1103382000,"dewPoint":41.61,"humidity":0.74,"pressure":1028.66,"windSpeed":1.19,"windGust":4.92,"windGustTime":1103284800,"windBearing":55,"cloudCover":0.55,"uvIndex":2,"uvIndexTime":1103313600,"visibility":4.064,"temperatureMin":42.48,"temperatureMinTime":1103353200,"temperatureMax":63.55,"temperatureMaxTime":1103324400,"apparentTemperatureMin":42.48,"apparentTemperatureMinTime":1103353200,"apparentTemperatureMax":63.55,"apparentTemperatureMaxTime":1103324400},"2005":{"time":1134806400,"summary":"Rain throughout the day.","icon":"rain","sunriseTime":1134833103,"sunsetTime":1134867210,"moonPhase":0.58,"precipIntensity":0.0075,"precipIntensityMax":0.0392,"precipIntensityMaxTime":1134889200,"precipProbability":1,"precipType":"rain","temperatureHigh":45.21,"temperatureHighTime":1134864000,"temperatureLow":44.69,"temperatureLowTime":1134882000,"apparentTemperatureHigh":45.21,"apparentTemperatureHighTime":1134864000,"apparentTemperatureLow":43.35,"apparentTemperatureLowTime":1134885600,"dewPoint":40,"humidity":0.9,"pressure":1014.36,"windSpeed":1.99,"windGust":9.46,"windGustTime":1134885600,"windBearing":90,"cloudCover":0.94,"uvIndex":2,"uvIndexTime":1134849600,"visibility":3.666,"temperatureMin":39.05,"temperatureMinTime":1134810000,"temperatureMax":45.66,"temperatureMaxTime":1134889200,"apparentTemperatureMin":39.05,"apparentTemperatureMinTime":1134810000,"apparentTemperatureMax":45.66,"apparentTemperatureMaxTime":1134889200},"2006":{"time":1166342400,"summary":"Partly cloudy throughout the day.","icon":"clear-day","sunriseTime":1166369094,"sunsetTime":1166403204,"moonPhase":0.92,"precipIntensity":0,"precipIntensityMax":0,"precipProbability":0,"temperatureHigh":54,"temperatureHighTime":1166396400,"temperatureLow":28.49,"temperatureLowTime":1166454000,"apparentTemperatureHigh":54,"apparentTemperatureHighTime":1166396400,"apparentTemperatureLow":28.49,"apparentTemperatureLowTime":1166454000,"dewPoint":30.66,"humidity":0.73,"pressure":1019.57,"windSpeed":1.51,"windGust":7.97,"windGustTime":1166392800,"windBearing":335,"cloudCover":0.09,"uvIndex":2,"uvIndexTime":1166385600,"visibility":8.664,"temperatureMin":30.7,"temperatureMinTime":1166367600,"temperatureMax":54,"temperatureMaxTime":1166396400,"apparentTemperatureMin":30.7,"apparentTemperatureMinTime":1166367600,"apparentTemperatureMax":54,"apparentTemperatureMaxTime":1166396400},"2007":{"time":1197878400,"summary":"Light rain throughout the day.","icon":"rain","sunriseTime":1197905085,"sunsetTime":1197939199,"moonPhase":0.28,"precipIntensity":0.0078,"precipIntensityMax":0.0645,"precipIntensityMaxTime":1197961200,"precipProbability":1,"precipType":"rain","temperatureHigh":51.25,"temperatureHighTime":1197932400,"temperatureLow":48.41,"temperatureLowTime":1197993600,"apparentTemperatureHigh":51.25,"apparentTemperatureHighTime":1197932400,"apparentTemperatureLow":45.01,"apparentTemperatureLowTime":1197993600,"dewPoint":45.21,"humidity":0.9,"pressure":1015.34,"windSpeed":2.35,"windGust":7.71,"windGustTime":1197932400,"windBearing":143,"cloudCover":0.97,"uvIndex":2,"uvIndexTime":1197921600,"visibility":5.592,"temperatureMin":44.01,"temperatureMinTime":1197903600,"temperatureMax":51.25,"temperatureMaxTime":1197932400,"apparentTemperatureMin":44.01,"apparentTemperatureMinTime":1197903600,"apparentTemperatureMax":51.25,"apparentTemperatureMaxTime":1197932400},"2008":{"time":1229500800,"summary":"Clear throughout the day.","icon":"clear-day","sunriseTime":1229527512,"sunsetTime":1229561615,"moonPhase":0.71,"precipIntensity":0,"precipIntensityMax":0.0005,"precipIntensityMaxTime":1229536800,"precipProbability":0.1,"temperatureHigh":52.87,"temperatureHighTime":1229554800,"temperatureLow":33.66,"temperatureLowTime":1229616000,"apparentTemperatureHigh":52.87,"apparentTemperatureHighTime":1229554800,"apparentTemperatureLow":31.49,"apparentTemperatureLowTime":1229587200,"dewPoint":27.75,"humidity":0.68,"pressure":1015.34,"windSpeed":3.02,"windGust":11.25,"windGustTime":1229583600,"windBearing":305,"cloudCover":0,"uvIndex":2,"uvIndexTime":1229544000,"visibility":9.997,"temperatureMin":28.65,"temperatureMinTime":1229529600,"temperatureMax":52.87,"temperatureMaxTime":1229554800,"apparentTemperatureMin":28.65,"apparentTemperatureMinTime":1229529600,"apparentTemperatureMax":52.87,"apparentTemperatureMaxTime":1229554800},"2009":{"time":1261036800,"summary":"Foggy until morning, starting again in the evening.","icon":"partly-cloudy-day","sunriseTime":1261063503,"sunsetTime":1261097610,"moonPhase":0.05,"precipIntensity":0,"precipIntensityMax":0,"precipProbability":0,"temperatureHigh":56.73,"temperatureHighTime":1261090800,"temperatureLow":46.96,"temperatureLowTime":1261130400,"apparentTemperatureHigh":56.73,"apparentTemperatureHighTime":1261090800,"apparentTemperatureLow":46.96,"apparentTemperatureLowTime":1261130400,"dewPoint":47.82,"humidity":0.89,"pressure":1022.95,"windSpeed":1.16,"windGust":4.34,"windGustTime":1261076400,"windBearing":47,"cloudCover":0.68,"uvIndex":2,"uvIndexTime":1261080000,"visibility":5.367,"temperatureMin":46.76,"temperatureMinTime":1261065600,"temperatureMax":56.73,"temperatureMaxTime":1261090800,"apparentTemperatureMin":46.76,"apparentTemperatureMinTime":1261065600,"apparentTemperatureMax":56.73,"apparentTemperatureMaxTime":1261090800},"2010":{"time":1292572800,"summary":"Rain throughout the day.","icon":"rain","sunriseTime":1292599495,"sunsetTime":1292633605,"moonPhase":0.39,"precipIntensity":0.0308,"precipIntensityMax":0.1179,"precipIntensityMaxTime":1292644800,"precipProbability":1,"precipType":"rain","temperatureHigh":47.28,"temperatureHighTime":1292626800,"temperatureLow":47.12,"temperatureLowTime":1292641200,"apparentTemperatureHigh":47.25,"apparentTemperatureHighTime":1292630400,"apparentTemperatureLow":45.59,"apparentTemperatureLowTime":1292641200,"dewPoint":43.26,"humidity":0.89,"pressure":1007.96,"windSpeed":2.92,"windGust":12.33,"windGustTime":1292655600,"windBearing":106,"cloudCover":1,"uvIndex":2,"uvIndexTime":1292616000,"visibility":5.404,"temperatureMin":43.42,"temperatureMinTime":1292594400,"temperatureMax":51.49,"temperatureMaxTime":1292655600,"apparentTemperatureMin":43.42,"apparentTemperatureMinTime":1292594400,"apparentTemperatureMax":51.49,"apparentTemperatureMaxTime":1292655600},"2011":{"time":1324108800,"summary":"Foggy in the morning and overnight.","icon":"partly-cloudy-day","sunriseTime":1324135486,"sunsetTime":1324169600,"moonPhase":0.76,"precipIntensity":0,"precipIntensityMax":0,"precipProbability":0,"temperatureHigh":61.65,"temperatureHighTime":1324162800,"temperatureLow":39.49,"temperatureLowTime":1324202400,"apparentTemperatureHigh":61.65,"apparentTemperatureHighTime":1324162800,"apparentTemperatureLow":39.49,"apparentTemperatureLowTime":1324202400,"dewPoint":37.12,"humidity":0.67,"pressure":1019.79,"windSpeed":1.34,"windGust":4.87,"windGustTime":1324130400,"windBearing":127,"cloudCover":0.34,"uvIndex":2,"uvIndexTime":1324152000,"visibility":7.897,"temperatureMin":38.83,"temperatureMinTime":1324137600,"temperatureMax":61.65,"temperatureMaxTime":1324162800,"apparentTemperatureMin":38.83,"apparentTemperatureMinTime":1324137600,"apparentTemperatureMax":61.65,"apparentTemperatureMaxTime":1324162800},"2012":{"time":1355731200,"summary":"Light rain in the morning.","icon":"rain","sunriseTime":1355757913,"sunsetTime":1355792015,"moonPhase":0.18,"precipIntensity":0.0109,"precipIntensityMax":0.0631,"precipIntensityMaxTime":1355734800,"precipProbability":1,"precipType":"rain","temperatureHigh":57.13,"temperatureHighTime":1355781600,"temperatureLow":34.77,"temperatureLowTime":1355842800,"apparentTemperatureHigh":57.13,"apparentTemperatureHighTime":1355781600,"apparentTemperatureLow":34.77,"apparentTemperatureLowTime":1355842800,"dewPoint":47.18,"humidity":0.85,"pressure":1014.73,"windSpeed":3.03,"windGust":12.08,"windGustTime":1355742000,"windBearing":255,"cloudCover":0.7,"uvIndex":2,"uvIndexTime":1355774400,"visibility":7.832,"temperatureMin":43.34,"temperatureMinTime":1355810400,"temperatureMax":57.13,"temperatureMaxTime":1355781600,"apparentTemperatureMin":43.34,"apparentTemperatureMinTime":1355810400,"apparentTemperatureMax":57.13,"apparentTemperatureMaxTime":1355781600},"2013":{"time":1387267200,"summary":"Partly cloudy throughout the day.","icon":"partly-cloudy-day","sunriseTime":1387293904,"sunsetTime":1387328010,"moonPhase":0.52,"precipIntensity":0,"precipIntensityMax":0,"precipProbability":0,"temperatureHigh":65.44,"temperatureHighTime":1387317600,"temperatureLow":39.4,"temperatureLowTime":1387378800,"apparentTemperatureHigh":65.44,"apparentTemperatureHighTime":1387317600,"apparentTemperatureLow":39.4,"apparentTemperatureLowTime":1387378800,"dewPoint":36.25,"humidity":0.63,"pressure":1020.32,"windSpeed":0.63,"windGust":2.74,"windGustTime":1387314000,"windBearing":82,"cloudCover":0.27,"uvIndex":2,"uvIndexTime":1387310400,"visibility":9.282,"temperatureMin":39.44,"temperatureMinTime":1387296000,"temperatureMax":65.44,"temperatureMaxTime":1387317600,"apparentTemperatureMin":39.44,"apparentTemperatureMinTime":1387296000,"apparentTemperatureMax":65.44,"apparentTemperatureMaxTime":1387317600},"2014":{"time":1418803200,"summary":"Light rain throughout the day.","icon":"rain","sunriseTime":1418829895,"sunsetTime":1418864005,"moonPhase":0.86,"precipIntensity":0.0124,"precipIntensityMax":0.0265,"precipIntensityMaxTime":1418875200,"precipProbability":1,"precipType":"rain","temperatureHigh":55.01,"temperatureHighTime":1418850000,"temperatureLow":49.53,"temperatureLowTime":1418878800,"apparentTemperatureHigh":55.01,"apparentTemperatureHighTime":1418850000,"apparentTemperatureLow":48.98,"apparentTemperatureLowTime":1418878800,"dewPoint":47.83,"humidity":0.9,"pressure":1015.07,"windSpeed":1.24,"windGust":5.61,"windGustTime":1418878800,"windBearing":126,"cloudCover":0.96,"uvIndex":2,"uvIndexTime":1418846400,"visibility":5.781,"temperatureMin":48.64,"temperatureMinTime":1418806800,"temperatureMax":55.01,"temperatureMaxTime":1418850000,"apparentTemperatureMin":48.64,"apparentTemperatureMinTime":1418806800,"apparentTemperatureMax":55.01,"apparentTemperatureMaxTime":1418850000},"2015":{"time":1450339200,"summary":"Possible drizzle until morning, starting again in the evening.","icon":"rain","sunriseTime":1450365886,"sunsetTime":1450400000,"moonPhase":0.23,"precipIntensity":0.0009,"precipIntensityMax":0.0041,"precipIntensityMaxTime":1450418400,"precipProbability":0.61,"precipType":"rain","temperatureHigh":51.74,"temperatureHighTime":1450393200,"temperatureLow":48.91,"temperatureLowTime":1450432800,"apparentTemperatureHigh":51.74,"apparentTemperatureHighTime":1450393200,"apparentTemperatureLow":48.91,"apparentTemperatureLowTime":1450432800,"dewPoint":42.15,"humidity":0.85,"pressure":1023.07,"windSpeed":0.6,"windGust":2.22,"windGustTime":1450382400,"windBearing":108,"cloudCover":0.9,"uvIndex":2,"uvIndexTime":1450382400,"visibility":7.921,"temperatureMin":40.87,"temperatureMinTime":1450350000,"temperatureMax":51.74,"temperatureMaxTime":1450393200,"apparentTemperatureMin":40.87,"apparentTemperatureMinTime":1450350000,"apparentTemperatureMax":51.74,"apparentTemperatureMaxTime":1450393200},"2016":{"time":1481961600,"summary":"Clear throughout the day.","icon":"clear-day","sunriseTime":1481988313,"sunsetTime":1482022416,"moonPhase":0.66,"precipIntensity":0,"precipIntensityMax":0,"precipProbability":0,"temperatureHigh":50.99,"temperatureHighTime":1482015600,"temperatureLow":30.1,"temperatureLowTime":1482073200,"apparentTemperatureHigh":50.99,"apparentTemperatureHighTime":1482015600,"apparentTemperatureLow":30.1,"apparentTemperatureLowTime":1482073200,"dewPoint":31.06,"humidity":0.73,"pressure":1023.72,"windSpeed":1,"windGust":4.99,"windGustTime":1482012000,"windBearing":331,"cloudCover":0,"uvIndex":2,"uvIndexTime":1482004800,"visibility":9.997,"temperatureMin":31.52,"temperatureMinTime":1481986800,"temperatureMax":50.99,"temperatureMaxTime":1482015600,"apparentTemperatureMin":31.52,"apparentTemperatureMinTime":1481986800,"apparentTemperatureMax":50.99,"apparentTemperatureMaxTime":1482015600},"2017":{"time":1513497600,"summary":"Clear throughout the day.","icon":"clear-day","sunriseTime":1513524304,"sunsetTime":1513558410,"moonPhase":1,"precipIntensity":0,"precipIntensityMax":0,"precipProbability":0,"temperatureHigh":68.21,"temperatureHighTime":1513548000,"temperatureLow":37.35,"temperatureLowTime":1513612800,"apparentTemperatureHigh":68.21,"apparentTemperatureHighTime":1513548000,"apparentTemperatureLow":37.35,"apparentTemperatureLowTime":1513612800,"dewPoint":33.86,"humidity":0.5,"pressure":1015.96,"windSpeed":2.5,"windGust":12.22,"windGustTime":1513501200,"windBearing":351,"cloudCover":0.01,"uvIndex":2,"uvIndexTime":1513540800,"visibility":9.997,"temperatureMin":43.19,"temperatureMinTime":1513580400,"temperatureMax":68.21,"temperatureMaxTime":1513548000,"apparentTemperatureMin":43.19,"apparentTemperatureMinTime":1513580400,"apparentTemperatureMax":68.21,"apparentTemperatureMaxTime":1513548000},"2018":{"time":1545033600,"summary":"Foggy in the morning and overnight.","icon":"cloudy","sunriseTime":1545060295,"sunsetTime":1545094405,"moonPhase":0.34,"precipIntensity":0,"precipIntensityMax":0.0004,"precipIntensityMaxTime":1545033600,"precipProbability":0.33,"temperatureHigh":56.83,"temperatureHighTime":1545084000,"temperatureLow":47.53,"temperatureLowTime":1545141600,"apparentTemperatureHigh":56.83,"apparentTemperatureHighTime":1545084000,"apparentTemperatureLow":47.53,"apparentTemperatureLowTime":1545141600,"dewPoint":42.67,"humidity":0.72,"pressure":1021.32,"windSpeed":2.33,"windGust":6.67,"windGustTime":1545080400,"windBearing":172,"cloudCover":0.91,"uvIndex":2,"uvIndexTime":1545076800,"visibility":4.039,"ozone":301.7,"temperatureMin":46.69,"temperatureMinTime":1545058800,"temperatureMax":56.83,"temperatureMaxTime":1545084000,"apparentTemperatureMin":46.69,"apparentTemperatureMinTime":1545058800,"apparentTemperatureMax":56.83,"apparentTemperatureMaxTime":1545084000}}