{"1944":{"time":-814035600,"summary":"Clear throughout the day.","icon":"clear-day","sunriseTime":-814009071,"sunsetTime":-813965957,"moonPhase":0.73,"precipType":"rain","temperatureHigh":64.09,"temperatureHighTime":-813985200,"temperatureLow":42.14,"temperatureLowTime":-813924000,"apparentTemperatureHigh":64.09,"apparentTemperatureHighTime":-813985200,"apparentTemperatureLow":38.41,"apparentTemperatureLowTime":-813924000,"dewPoint":43.2,"humidity":0.8,"pressure":1018.11,"windSpeed":5.32,"windBearing":157,"uvIndex":0,"uvIndexTime":-814035600,"temperatureMin":37.22,"temperatureMinTime":-814014000,"temperatureMax":64.09,"temperatureMaxTime":-813985200,"apparentTemperatureMin":35.57,"apparentTemperatureMinTime":-814017600,"apparentTemperatureMax":64.09,"apparentTemperatureMaxTime":-813985200},"1945":{"time":-782499600,"summary":"Clear throughout the day.","icon":"clear-day","sunriseTime":-782473048,"sunsetTime":-782429971,"moonPhase":0.12,"precipType":"rain","temperatureHigh":50.04,"temperatureHighTime":-782431200,"temperatureLow":42.44,"temperatureLowTime":-782384400,"apparentTemperatureHigh":50.04,"apparentTemperatureHighTime":-782431200,"apparentTemperatureLow":38.77,"apparentTemperatureLowTime":-782384400,"dewPoint":41.45,"humidity":0.9,"pressure":1011.05,"windSpeed":13.81,"windBearing":140,"uvIndex":0,"uvIndexTime":-782499600,"temperatureMin":38.52,"temperatureMinTime":-782499600,"temperatureMax":50.04,"temperatureMaxTime":-782431200,"apparentTemperatureMin":33.93,"apparentTemperatureMinTime":-782496000,"apparentTemperatureMax":50.04,"apparentTemperatureMaxTime":-782431200},"1946":{"time":-750960000,"summary":"Clear throughout the day.","icon":"clear-day","sunriseTime":-750937029,"sunsetTime":-750893982,"moonPhase":0.48,"temperatureHigh":63,"temperatureHighTime":-750902400,"apparentTemperatureHigh":63,"apparentTemperatureHighTime":-750902400,"dewPoint":41.81,"humidity":0.63,"pressure":1018.57,"windSpeed":6.67,"windBearing":189,"uvIndex":0,"uvIndexTime":-750960000,"temperatureMin":36.02,"temperatureMinTime":-750934800,"temperatureMax":63,"temperatureMaxTime":-750902400,"apparentTemperatureMin":32.07,"apparentTemperatureMinTime":-750934800,"apparentTemperatureMax":63,"apparentTemperatureMaxTime":-750902400},"1947":{},"1948":{},"1949":{},"1950":{},"1951":{},"1952":{},"1953":{},"1954":{},"1955":{},"1956":{},"1957":{},"1958":{},"1959":{},"1960":{},"1961":{},"1962":{},"1963":{},"1964":{},"1965":{},"1966":{},"1967":{},"1968":{},"1969":{},"1970":{},"1971":{},"1972":{},"1973":{"time":101116800,"summary":"Foggy in the evening and overnight.","icon":"cloudy","sunriseTime":101139727,"sunsetTime":101182843,"moonPhase":0.44,"temperatureHigh":56.84,"temperatureHighTime":101163600,"temperatureLow":35.97,"temperatureLowTime":101228400,"apparentTemperatureHigh":56.84,"apparentTemperatureHighTime":101163600,"apparentTemperatureLow":31.27,"apparentTemperatureLowTime":101228400,"dewPoint":39.55,"humidity":0.66,"windSpeed":7.87,"windBearing":217,"cloudCover":1,"uvIndex":4,"uvIndexTime":101160000,"visibility":8.471,"temperatureMin":45.86,"temperatureMinTime":101142000,"temperatureMax":56.84,"temperatureMaxTime":101163600,"apparentTemperatureMin":41.34,"apparentTemperatureMinTime":101199600,"apparentTemperatureMax":56.84,"apparentTemperatureMaxTime":101163600},"1974":{"time":132649200,"summary":"Overcast throughout the day.","icon":"cloudy","sunriseTime":132675753,"sunsetTime":132718826,"moonPhase":0.79,"temperatureHigh":66.02,"temperatureHighTime":132703200,"temperatureLow":53.06,"temperatureLowTime":132721200,"apparentTemperatureHigh":66.02,"apparentTemperatureHighTime":132703200,"apparentTemperatureLow":53.06,"apparentTemperatureLowTime":132721200,"dewPoint":54.65,"humidity":0.91,"windSpeed":7.24,"windBearing":167,"cloudCover":0.98,"uvIndex":4,"uvIndexTime":132696000,"visibility":9.059,"temperatureMin":51.99,"temperatureMinTime":132674400,"temperatureMax":66.02,"temperatureMaxTime":132703200,"apparentTemperatureMin":51.99,"apparentTemperatureMinTime":132674400,"apparentTemperatureMax":66.02,"apparentTemperatureMaxTime":132703200},"1975":{"time":164185200,"summary":"Partly cloudy throughout the day.","icon":"partly-cloudy-day","sunriseTime":164211776,"sunsetTime":164254812,"moonPhase":0.13,"temperatureHigh":55.94,"temperatureHighTime":164242800,"temperatureLow":41,"temperatureLowTime":164268000,"apparentTemperatureHigh":55.94,"apparentTemperatureHighTime":164242800,"apparentTemperatureLow":37.67,"apparentTemperatureLowTime":164264400,"dewPoint":35.73,"humidity":0.66,"windSpeed":7.56,"windBearing":233,"cloudCover":0.3,"uvIndex":5,"uvIndexTime":164228400,"visibility":10,"temperatureMin":33.98,"temperatureMinTime":164210400,"temperatureMax":55.94,"temperatureMaxTime":164242800,"apparentTemperatureMin":33.98,"apparentTemperatureMinTime":164210400,"apparentTemperatureMax":55.94,"apparentTemperatureMaxTime":164242800},"1976":{"time":195811200,"summary":"Mostly cloudy throughout the day.","icon":"partly-cloudy-day","sunriseTime":195834102,"sunsetTime":195877259,"moonPhase":0.54,"windSpeed":2.38,"windBearing":194,"cloudCover":0.83,"uvIndex":4,"uvIndexTime":195858000,"visibility":9.998},"1977":{"time":227347200,"summary":"Overcast throughout the day.","icon":"cloudy","sunriseTime":227370124,"sunsetTime":227413245,"moonPhase":0.91,"windSpeed":3.02,"windBearing":236,"cloudCover":0.88,"uvIndex":4,"uvIndexTime":227394000,"visibility":8.588},"1978":{"time":258883200,"summary":"Partly cloudy throughout the day.","icon":"clear-day","sunriseTime":258906147,"sunsetTime":258949231,"moonPhase":0.26,"temperatureHigh":73.05,"temperatureHighTime":258937200,"temperatureLow":49.99,"temperatureLowTime":258998400,"apparentTemperatureHigh":73.05,"apparentTemperatureHighTime":258937200,"apparentTemperatureLow":49.99,"apparentTemperatureLowTime":258998400,"dewPoint":52.14,"humidity":0.69,"windSpeed":3.95,"windBearing":151,"cloudCover":0.1,"uvIndex":6,"uvIndexTime":258926400,"visibility":9.999,"temperatureMin":44.95,"temperatureMinTime":258912000,"temperatureMax":73.05,"temperatureMaxTime":258937200,"apparentTemperatureMin":44.95,"apparentTemperatureMinTime":258912000,"apparentTemperatureMax":73.05,"apparentTemperatureMaxTime":258937200},"1979":{"time":290419200,"summary":"Foggy in the evening.","icon":"cloudy","sunriseTime":290442170,"sunsetTime":290485217,"moonPhase":0.6,"temperatureHigh":53.97,"temperatureHighTime":290458800,"temperatureLow":39.92,"temperatureLowTime":290527200,"apparentTemperatureHigh":53.97,"apparentTemperatureHighTime":290458800,"apparentTemperatureLow":39.92,"apparentTemperatureLowTime":290527200,"dewPoint":46.06,"humidity":0.87,"windSpeed":5.48,"windBearing":138,"cloudCover":0.98,"uvIndex":4,"uvIndexTime":290466000,"visibility":5.687,"temperatureMin":46.05,"temperatureMinTime":290498400,"temperatureMax":53.97,"temperatureMaxTime":290458800,"apparentTemperatureMin":44.25,"apparentTemperatureMinTime":290444400,"apparentTemperatureMax":53.97,"apparentTemperatureMaxTime":290458800},"1980":{"time":322041600,"summary":"Clear throughout the day.","icon":"clear-day","sunriseTime":322064499,"sunsetTime":322107660,"moonPhase":0.02,"temperatureHigh":64.04,"temperatureHighTime":322095600,"temperatureLow":39.01,"temperatureLowTime":322149600,"apparentTemperatureHigh":64.04,"apparentTemperatureHighTime":322095600,"apparentTemperatureLow":39.01,"apparentTemperatureLowTime":322149600,"dewPoint":36.25,"humidity":0.52,"windSpeed":8.62,"windBearing":331,"cloudCover":0.07,"uvIndex":6,"uvIndexTime":322084800,"visibility":10,"temperatureMin":39.92,"temperatureMinTime":322066800,"temperatureMax":64.04,"temperatureMaxTime":322095600,"apparentTemperatureMin":36.55,"apparentTemperatureMinTime":322066800,"apparentTemperatureMax":64.04,"apparentTemperatureMaxTime":322095600},"1981":{"time":353577600,"summary":"Foggy in the morning.","icon":"partly-cloudy-day","sunriseTime":353600521,"sunsetTime":353643646,"moonPhase":0.39,"temperatureHigh":66.02,"temperatureHighTime":353638800,"apparentTemperatureHigh":66.02,"apparentTemperatureHighTime":353638800,"dewPoint":39.1,"humidity":0.7,"windSpeed":6.23,"windBearing":334,"cloudCover":0.32,"uvIndex":6,"uvIndexTime":353620800,"visibility":8.021,"temperatureMin":37.04,"temperatureMinTime":353602800,"temperatureMax":66.02,"temperatureMaxTime":353638800,"apparentTemperatureMin":37.04,"apparentTemperatureMinTime":353602800,"apparentTemperatureMax":66.02,"apparentTemperatureMaxTime":353638800},"1982":{"time":385113600,"summary":"Overcast throughout the day.","icon":"cloudy","sunriseTime":385136544,"sunsetTime":385179632,"moonPhase":0.73,"temperatureHigh":53.06,"temperatureHighTime":385167600,"apparentTemperatureHigh":53.06,"apparentTemperatureHighTime":385167600,"dewPoint":38.82,"humidity":0.73,"windSpeed":5.44,"windBearing":168,"cloudCover":0.92,"uvIndex":4,"uvIndexTime":385156800,"visibility":9.385,"temperatureMin":42.07,"temperatureMinTime":385185600,"temperatureMax":53.06,"temperatureMaxTime":385167600,"apparentTemperatureMin":37.79,"apparentTemperatureMinTime":385185600,"apparentTemperatureMax":53.06,"apparentTemperatureMaxTime":385167600},"1983":{"time":416649600,"summary":"Foggy in the afternoon.","icon":"cloudy","sunriseTime":416672567,"sunsetTime":416715618,"moonPhase":0.08,"temperatureHigh":55.04,"temperatureHighTime":416707200,"apparentTemperatureHigh":55.04,"apparentTemperatureHighTime":416707200,"dewPoint":32.02,"humidity":0.5,"windSpeed":7.07,"windBearing":135,"cloudCover":0.89,"uvIndex":4,"uvIndexTime":416696400,"visibility":7.923,"temperatureMin":41,"temperatureMinTime":416674800,"temperatureMax":55.04,"temperatureMaxTime":416707200,"apparentTemperatureMin":37.22,"apparentTemperatureMinTime":416674800,"apparentTemperatureMax":55.04,"apparentTemperatureMaxTime":416707200},"1984":{"time":448272000,"summary":"Foggy in the afternoon and evening.","icon":"cloudy","sunriseTime":448294896,"sunsetTime":448338062,"moonPhase":0.49,"temperatureHigh":60.09,"temperatureHighTime":448318800,"apparentTemperatureHigh":60.09,"apparentTemperatureHighTime":448318800,"dewPoint":48.3,"humidity":0.87,"windSpeed":10.32,"windBearing":153,"cloudCover":0.98,"uvIndex":4,"uvIndexTime":448315200,"visibility":7.337,"temperatureMin":42.98,"temperatureMinTime":448297200,"temperatureMax":60.09,"temperatureMaxTime":448318800,"apparentTemperatureMin":41.76,"apparentTemperatureMinTime":448300800,"apparentTemperatureMax":60.09,"apparentTemperatureMaxTime":448318800},"1985":{"time":479808000,"summary":"Overcast throughout the day.","icon":"cloudy","sunriseTime":479830918,"sunsetTime":479874048,"moonPhase":0.87,"temperatureHigh":57.92,"temperatureHighTime":479862000,"apparentTemperatureHigh":57.92,"apparentTemperatureHighTime":479862000,"dewPoint":44.54,"humidity":0.75,"windSpeed":4.75,"windBearing":199,"cloudCover":0.89,"uvIndex":4,"uvIndexTime":479854800,"visibility":8.286,"temperatureMin":48.02,"temperatureMinTime":479833200,"temperatureMax":57.92,"temperatureMaxTime":479862000,"apparentTemperatureMin":45.41,"apparentTemperatureMinTime":479876400,"apparentTemperatureMax":57.92,"apparentTemperatureMaxTime":479862000},"1986":{"time":511344000,"summary":"Mostly cloudy throughout the day.","icon":"partly-cloudy-day","sunriseTime":511366941,"sunsetTime":511410034,"moonPhase":0.21,"temperatureHigh":62.06,"temperatureHighTime":511398000,"temperatureLow":48.02,"temperatureLowTime":511455600,"apparentTemperatureHigh":62.06,"apparentTemperatureHighTime":511398000,"apparentTemperatureLow":46.1,"apparentTemperatureLowTime":511455600,"dewPoint":44.82,"humidity":0.73,"windSpeed":9.92,"windBearing":354,"cloudCover":0.65,"uvIndex":5,"uvIndexTime":511394400,"visibility":10,"temperatureMin":48.02,"temperatureMinTime":511369200,"temperatureMax":62.06,"temperatureMaxTime":511398000,"apparentTemperatureMin":43.48,"apparentTemperatureMinTime":511369200,"apparentTemperatureMax":62.06,"apparentTemperatureMaxTime":511398000},"1987":{"time":542880000,"summary":"Partly cloudy throughout the day.","icon":"partly-cloudy-day","sunriseTime":542902964,"sunsetTime":542946020,"moonPhase":0.56,"temperatureHigh":69.09,"temperatureHighTime":542934000,"temperatureLow":41,"temperatureLowTime":542991600,"apparentTemperatureHigh":69.09,"apparentTemperatureHighTime":542934000,"apparentTemperatureLow":37.07,"apparentTemperatureLowTime":542991600,"dewPoint":42.64,"humidity":0.54,"windSpeed":7.54,"windBearing":315,"cloudCover":0.24,"uvIndex":6,"uvIndexTime":542923200,"visibility":9.999,"temperatureMin":44.95,"temperatureMinTime":542905200,"temperatureMax":69.09,"temperatureMaxTime":542934000,"apparentTemperatureMin":41.76,"apparentTemperatureMinTime":542905200,"apparentTemperatureMax":69.09,"apparentTemperatureMaxTime":542934000},"1988":{"time":574502400,"summary":"Foggy in the morning.","icon":"partly-cloudy-day","sunriseTime":574525292,"sunsetTime":574568464,"moonPhase":0.97,"temperatureHigh":64.94,"temperatureHighTime":574556400,"temperatureLow":37.93,"temperatureLowTime":574614000,"apparentTemperatureHigh":64.94,"apparentTemperatureHighTime":574556400,"apparentTemperatureLow":37.93,"apparentTemperatureLowTime":574614000,"dewPoint":44.25,"humidity":0.84,"windSpeed":5.68,"windBearing":144,"cloudCover":0.41,"uvIndex":6,"uvIndexTime":574545600,"visibility":6.565,"temperatureMin":37.93,"temperatureMinTime":574527600,"temperatureMax":64.94,"temperatureMaxTime":574556400,"apparentTemperatureMin":37.93,"apparentTemperatureMinTime":574527600,"apparentTemperatureMax":64.94,"apparentTemperatureMaxTime":574556400},"1989":{"time":606038400,"summary":"Mostly cloudy throughout the day.","icon":"partly-cloudy-day","sunriseTime":606061315,"sunsetTime":606104450,"moonPhase":0.34,"temperatureHigh":55.94,"temperatureHighTime":606088800,"apparentTemperatureHigh":55.94,"apparentTemperatureHighTime":606088800,"dewPoint":42.49,"humidity":0.74,"windSpeed":8.86,"windBearing":225,"cloudCover":0.74,"uvIndex":6,"uvIndexTime":606085200,"visibility":8.999,"temperatureMin":46.05,"temperatureMinTime":606063600,"temperatureMax":55.94,"temperatureMaxTime":606088800,"apparentTemperatureMin":40.65,"apparentTemperatureMinTime":606063600,"apparentTemperatureMax":55.94,"apparentTemperatureMaxTime":606088800},"1990":{"time":637574400,"summary":"Foggy in the morning.","icon":"cloudy","sunriseTime":637597338,"sunsetTime":637640436,"moonPhase":0.68,"temperatureHigh":64.94,"temperatureHighTime":637624800,"apparentTemperatureHigh":64.94,"apparentTemperatureHighTime":637624800,"dewPoint":51.79,"humidity":0.83,"windSpeed":4.28,"windBearing":185,"cloudCover":0.99,"uvIndex":4,"uvIndexTime":637617600,"visibility":3.205,"temperatureMin":46.05,"temperatureMinTime":637599600,"temperatureMax":64.94,"temperatureMaxTime":637624800,"apparentTemperatureMin":44.12,"apparentTemperatureMinTime":637603200,"apparentTemperatureMax":64.94,"apparentTemperatureMaxTime":637624800},"1991":{"time":669110400,"summary":"Overcast throughout the day.","icon":"cloudy","sunriseTime":669133361,"sunsetTime":669176422,"moonPhase":0.03,"temperatureHigh":51.08,"temperatureHighTime":669150000,"apparentTemperatureHigh":51.08,"apparentTemperatureHighTime":669150000,"dewPoint":41.33,"humidity":0.81,"windSpeed":12.75,"windBearing":113,"cloudCover":1,"uvIndex":4,"uvIndexTime":669153600,"visibility":8.077,"temperatureMin":39.01,"temperatureMinTime":669135600,"temperatureMax":51.08,"temperatureMaxTime":669150000,"apparentTemperatureMin":39.01,"apparentTemperatureMinTime":669135600,"apparentTemperatureMax":51.08,"apparentTemperatureMaxTime":669150000},"1992":{"time":700732800,"summary":"Mostly cloudy throughout the day.","icon":"partly-cloudy-day","sunriseTime":700755689,"sunsetTime":700798865,"moonPhase":0.44,"temperatureHigh":60.09,"temperatureHighTime":700786800,"apparentTemperatureHigh":60.09,"apparentTemperatureHighTime":700786800,"dewPoint":50,"humidity":0.85,"windSpeed":10.2,"windBearing":259,"cloudCover":0.77,"uvIndex":4,"uvIndexTime":700776000,"visibility":8.713,"temperatureMin":48.93,"temperatureMinTime":700758000,"temperatureMax":60.09,"temperatureMaxTime":700786800,"apparentTemperatureMin":45,"apparentTemperatureMinTime":700758000,"apparentTemperatureMax":60.09,"apparentTemperatureMaxTime":700786800},"1993":{"time":732268800,"summary":"Overcast throughout the day.","icon":"cloudy","sunriseTime":732291712,"sunsetTime":732334851,"moonPhase":0.81,"temperatureHigh":60.99,"temperatureHighTime":732312000,"apparentTemperatureHigh":60.99,"apparentTemperatureHighTime":732312000,"dewPoint":50,"humidity":0.81,"windSpeed":1.93,"windBearing":124,"cloudCover":0.98,"uvIndex":4,"uvIndexTime":732312000,"visibility":8.25,"temperatureMin":48.93,"temperatureMinTime":732294000,"temperatureMax":60.99,"temperatureMaxTime":732312000,"apparentTemperatureMin":48.93,"apparentTemperatureMinTime":732294000,"apparentTemperatureMax":60.99,"apparentTemperatureMaxTime":732312000},"1994":{"time":763804800,"summary":"Mostly cloudy throughout the day.","icon":"partly-cloudy-day","sunriseTime":763827735,"sunsetTime":763870837,"moonPhase":0.15,"temperatureHigh":62.96,"temperatureHighTime":763851600,"apparentTemperatureHigh":62.96,"apparentTemperatureHighTime":763851600,"dewPoint":46.76,"humidity":0.68,"windSpeed":9.78,"windBearing":209,"cloudCover":0.65,"uvIndex":4,"uvIndexTime":763848000,"visibility":9.214,"temperatureMin":48.93,"temperatureMinTime":763876800,"temperatureMax":62.96,"temperatureMaxTime":763851600,"apparentTemperatureMin":46.03,"apparentTemperatureMinTime":763876800,"apparentTemperatureMax":62.96,"apparentTemperatureMaxTime":763851600},"1995":{"time":795340800,"summary":"Foggy in the morning.","icon":"clear-day","sunriseTime":795363757,"sunsetTime":795406823,"moonPhase":0.51,"temperatureHigh":68,"temperatureHighTime":795394800,"temperatureLow":42.98,"temperatureLowTime":795445200,"apparentTemperatureHigh":68,"apparentTemperatureHighTime":795394800,"apparentTemperatureLow":42.98,"apparentTemperatureLowTime":795445200,"dewPoint":47.89,"humidity":0.71,"windSpeed":5.35,"windBearing":125,"cloudCover":0.04,"uvIndex":6,"uvIndexTime":795384000,"visibility":8.712,"temperatureMin":42.98,"temperatureMinTime":795366000,"temperatureMax":68,"temperatureMaxTime":795394800,"apparentTemperatureMin":42.98,"apparentTemperatureMinTime":795366000,"apparentTemperatureMax":68,"apparentTemperatureMaxTime":795394800},"1996":{"time":826963200,"summary":"Foggy in the morning.","icon":"partly-cloudy-day","sunriseTime":826986086,"sunsetTime":827029267,"moonPhase":0.92,"temperatureHigh":72.85,"temperatureHighTime":827013600,"apparentTemperatureHigh":72.85,"apparentTemperatureHighTime":827013600,"dewPoint":52.78,"humidity":0.78,"windSpeed":4.38,"windBearing":146,"cloudCover":0.55,"uvIndex":6,"uvIndexTime":827010000,"visibility":7.517,"temperatureMin":48.93,"temperatureMinTime":826988400,"temperatureMax":72.85,"temperatureMaxTime":827013600,"apparentTemperatureMin":48.93,"apparentTemperatureMinTime":826988400,"apparentTemperatureMax":72.85,"apparentTemperatureMaxTime":827013600},"1997":{"time":858499200,"summary":"Foggy until evening.","icon":"cloudy","sunriseTime":858522109,"sunsetTime":858565253,"moonPhase":0.29,"temperatureHigh":53.6,"temperatureHighTime":858546000,"apparentTemperatureHigh":53.6,"apparentTemperatureHighTime":858546000,"dewPoint":51.02,"humidity":0.95,"windSpeed":8.59,"windBearing":151,"cloudCover":1,"uvIndex":4,"uvIndexTime":858546000,"visibility":2.214,"temperatureMin":49.99,"temperatureMinTime":858524400,"temperatureMax":53.6,"temperatureMaxTime":858546000,"apparentTemperatureMin":49.99,"apparentTemperatureMinTime":858524400,"apparentTemperatureMax":53.6,"apparentTemperatureMaxTime":858546000},"1998":{"time":890035200,"summary":"Partly cloudy throughout the day.","icon":"partly-cloudy-day","sunriseTime":890058132,"sunsetTime":890101239,"moonPhase":0.62,"temperatureHigh":73.39,"temperatureHighTime":890085600,"apparentTemperatureHigh":73.39,"apparentTemperatureHighTime":890085600,"dewPoint":53.21,"humidity":0.68,"windSpeed":6.42,"windBearing":175,"cloudCover":0.49,"uvIndex":5,"uvIndexTime":890078400,"visibility":10,"temperatureMin":49.99,"temperatureMinTime":890060400,"temperatureMax":73.39,"temperatureMaxTime":890085600,"apparentTemperatureMin":49.99,"apparentTemperatureMinTime":890060400,"apparentTemperatureMax":73.39,"apparentTemperatureMaxTime":890085600},"1999":{"time":921571200,"summary":"Foggy in the morning.","icon":"partly-cloudy-day","sunriseTime":921594154,"sunsetTime":921637225,"moonPhase":0.98,"precipType":"rain","temperatureHigh":62.6,"temperatureHighTime":921618000,"temperatureLow":46.41,"temperatureLowTime":921646800,"apparentTemperatureHigh":62.6,"apparentTemperatureHighTime":921618000,"apparentTemperatureLow":41.9,"apparentTemperatureLowTime":921646800,"dewPoint":43.32,"humidity":0.84,"pressure":1014.17,"windSpeed":4.91,"windBearing":158,"cloudCover":0.49,"uvIndex":6,"uvIndexTime":921614400,"visibility":6.436,"temperatureMin":37.4,"temperatureMinTime":921596400,"temperatureMax":62.6,"temperatureMaxTime":921618000,"apparentTemperatureMin":37.07,"apparentTemperatureMinTime":921585600,"apparentTemperatureMax":62.6,"apparentTemperatureMaxTime":921618000},"2000":{"time":953193600,"summary":"Clear throughout the day.","icon":"partly-cloudy-day","sunriseTime":953216483,"sunsetTime":953259668,"moonPhase":0.39,"precipType":"rain","temperatureHigh":69.77,"temperatureHighTime":953244000,"temperatureLow":40.96,"temperatureLowTime":953301600,"apparentTemperatureHigh":69.77,"apparentTemperatureHighTime":953244000,"apparentTemperatureLow":35.19,"apparentTemperatureLowTime":953301600,"dewPoint":40.71,"humidity":0.55,"pressure":1019.65,"windSpeed":11.28,"windBearing":318,"cloudCover":0.14,"uvIndex":6,"uvIndexTime":953236800,"visibility":9.997,"temperatureMin":48.17,"temperatureMinTime":953276400,"temperatureMax":69.77,"temperatureMaxTime":953244000,"apparentTemperatureMin":43.31,"apparentTemperatureMinTime":953276400,"apparentTemperatureMax":69.77,"apparentTemperatureMaxTime":953244000},"2001":{"time":984729600,"summary":"Clear throughout the day.","icon":"clear-day","sunriseTime":984752506,"sunsetTime":984795654,"moonPhase":0.76,"precipType":"rain","temperatureHigh":64.9,"temperatureHighTime":984780000,"temperatureLow":44.02,"temperatureLowTime":984837600,"apparentTemperatureHigh":64.9,"apparentTemperatureHighTime":984780000,"apparentTemperatureLow":42.55,"apparentTemperatureLowTime":984841200,"dewPoint":41.34,"humidity":0.65,"pressure":1016.83,"windSpeed":3.98,"windBearing":232,"cloudCover":0,"uvIndex":6,"uvIndexTime":984772800,"visibility":9.649,"temperatureMin":40.96,"temperatureMinTime":984754800,"temperatureMax":64.9,"temperatureMaxTime":984780000,"apparentTemperatureMin":39.06,"apparentTemperatureMinTime":984754800,"apparentTemperatureMax":64.9,"apparentTemperatureMaxTime":984780000},"2002":{"time":1016265600,"summary":"Partly cloudy throughout the day.","icon":"partly-cloudy-day","sunriseTime":1016288529,"sunsetTime":1016331640,"moonPhase":0.09,"precipType":"rain","temperatureHigh":54.6,"temperatureHighTime":1016316000,"temperatureLow":39.92,"temperatureLowTime":1016362800,"apparentTemperatureHigh":54.6,"apparentTemperatureHighTime":1016316000,"apparentTemperatureLow":36.38,"apparentTemperatureLowTime":1016362800,"dewPoint":30.74,"humidity":0.57,"pressure":1018.27,"windSpeed":11.36,"windGust":29,"windGustTime":1016272800,"windBearing":294,"cloudCover":0.24,"uvIndex":5,"uvIndexTime":1016305200,"visibility":9.997,"temperatureMin":39.18,"temperatureMinTime":1016287200,"temperatureMax":54.6,"temperatureMaxTime":1016316000,"apparentTemperatureMin":33.15,"apparentTemperatureMinTime":1016283600,"apparentTemperatureMax":54.6,"apparentTemperatureMaxTime":1016316000},"2003":{"time":1047801600,"summary":"Rain in the morning and afternoon.","icon":"rain","sunriseTime":1047824551,"sunsetTime":1047867626,"moonPhase":0.45,"precipIntensity":0.018,"precipIntensityMax":0.125,"precipIntensityMaxTime":1047859200,"precipProbability":1,"precipType":"rain","temperatureHigh":62.14,"temperatureHighTime":1047852000,"temperatureLow":43.62,"temperatureLowTime":1047906000,"apparentTemperatureHigh":62.14,"apparentTemperatureHighTime":1047852000,"apparentTemperatureLow":41.32,"apparentTemperatureLowTime":1047898800,"dewPoint":44.47,"humidity":0.74,"pressure":1007.52,"windSpeed":3.78,"windGust":16.23,"windGustTime":1047859200,"windBearing":288,"cloudCover":0.6,"uvIndex":5,"uvIndexTime":1047841200,"visibility":8.156,"temperatureMin":47.07,"temperatureMinTime":1047884400,"temperatureMax":62.14,"temperatureMaxTime":1047852000,"apparentTemperatureMin":45.4,"apparentTemperatureMinTime":1047884400,"apparentTemperatureMax":62.14,"apparentTemperatureMaxTime":1047852000},"2004":{"time":1079424000,"summary":"Clear throughout the day.","icon":"clear-day","sunriseTime":1079446880,"sunsetTime":1079490070,"moonPhase":0.87,"precipIntensity":0,"precipIntensityMax":0,"precipProbability":0,"temperatureHigh":87.95,"temperatureHighTime":1079478000,"temperatureLow":51.77,"temperatureLowTime":1079524800,"apparentTemperatureHigh":87.95,"apparentTemperatureHighTime":1079478000,"apparentTemperatureLow":51.77,"apparentTemperatureLowTime":1079524800,"dewPoint":41.3,"humidity":0.37,"pressure":1017.11,"windSpeed":2.63,"windGust":10.47,"windGustTime":1079460000,"windBearing":317,"cloudCover":0,"uvIndex":6,"uvIndexTime":1079467200,"visibility":9.997,"temperatureMin":57.66,"temperatureMinTime":1079449200,"temperatureMax":87.95,"temperatureMaxTime":1079478000,"apparentTemperatureMin":57.66,"apparentTemperatureMinTime":1079449200,"apparentTemperatureMax":87.95,"apparentTemperatureMaxTime":1079478000},"2005":{"time":1110960000,"summary":"Overcast throughout the day.","icon":"partly-cloudy-day","sunriseTime":1110982903,"sunsetTime":1111026056,"moonPhase":0.23,"precipIntensity":0,"precipIntensityMax":0,"precipProbability":0,"temperatureHigh":65.38,"temperatureHighTime":1111010400,"temperatureLow":48.6,"temperatureLowTime":1111057200,"apparentTemperatureHigh":65.38,"apparentTemperatureHighTime":1111010400,"apparentTemperatureLow":48.6,"apparentTemperatureLowTime":1111057200,"dewPoint":44.85,"humidity":0.71,"pressure":1018.63,"windSpeed":2.15,"windGust":9.96,"windGustTime":1111017600,"windBearing":174,"cloudCover":0.44,"uvIndex":6,"uvIndexTime":1111003200,"visibility":8.997,"temperatureMin":47.78,"temperatureMinTime":1110970800,"temperatureMax":65.38,"temperatureMaxTime":1111010400,"apparentTemperatureMin":47.78,"apparentTemperatureMinTime":1110970800,"apparentTemperatureMax":65.38,"apparentTemperatureMaxTime":1111010400},"2006":{"time":1142496000,"summary":"Light rain throughout the day.","icon":"rain","sunriseTime":1142518926,"sunsetTime":1142562042,"moonPhase":0.57,"precipIntensity":0.0153,"precipIntensityMax":0.0855,"precipIntensityMaxTime":1142557200,"precipProbability":1,"precipType":"rain","temperatureHigh":53.78,"temperatureHighTime":1142550000,"temperatureLow":43.81,"temperatureLowTime":1142607600,"apparentTemperatureHigh":53.78,"apparentTemperatureHighTime":1142550000,"apparentTemperatureLow":43.81,"apparentTemperatureLowTime":1142607600,"dewPoint":46.27,"humidity":0.88,"pressure":1016.42,"windSpeed":4.41,"windGust":15.96,"windGustTime":1142546400,"windBearing":153,"cloudCover":1,"uvIndex":4,"uvIndexTime":1142539200,"visibility":8.331,"temperatureMin":47.31,"temperatureMinTime":1142503200,"temperatureMax":53.78,"temperatureMaxTime":1142550000,"apparentTemperatureMin":45.67,"apparentTemperatureMinTime":1142503200,"apparentTemperatureMax":53.78,"apparentTemperatureMaxTime":1142550000},"2007":{"time":1174028400,"summary":"Clear throughout the day.","icon":"clear-day","sunriseTime":1174054951,"sunsetTime":1174098025,"moonPhase":0.92,"precipIntensity":0,"precipIntensityMax":0,"precipProbability":0,"temperatureHigh":82.38,"temperatureHighTime":1174086000,"temperatureLow":45.23,"temperatureLowTime":1174140000,"apparentTemperatureHigh":82.38,"apparentTemperatureHighTime":1174086000,"apparentTemperatureLow":45.23,"apparentTemperatureLowTime":1174140000,"dewPoint":46.61,"humidity":0.63,"pressure":1015.88,"windSpeed":1.8,"windGust":8.69,"windGustTime":1174086000,"windBearing":179,"cloudCover":0,"uvIndex":6,"uvIndexTime":1174075200,"visibility":9.539,"temperatureMin":45.76,"temperatureMinTime":1174053600,"temperatureMax":82.38,"temperatureMaxTime":1174086000,"apparentTemperatureMin":45.76,"apparentTemperatureMinTime":1174053600,"apparentTemperatureMax":82.38,"apparentTemperatureMaxTime":1174086000},"2008":{"time":1205650800,"summary":"Partly cloudy throughout the day.","icon":"clear-day","sunriseTime":1205677280,"sunsetTime":1205720468,"moonPhase":0.35,"precipIntensity":0,"precipIntensityMax":0,"precipProbability":0,"temperatureHigh":64.49,"temperatureHighTime":1205712000,"temperatureLow":38.65,"temperatureLowTime":1205762400,"apparentTemperatureHigh":64.49,"apparentTemperatureHighTime":1205712000,"apparentTemperatureLow":38.65,"apparentTemperatureLowTime":1205762400,"dewPoint":32.88,"humidity":0.53,"pressure":1018.17,"windSpeed":6.26,"windGust":15.81,"windGustTime":1205704800,"windBearing":337,"cloudCover":0.05,"uvIndex":6,"uvIndexTime":1205697600,"visibility":9.997,"temperatureMin":41.19,"temperatureMinTime":1205676000,"temperatureMax":64.49,"temperatureMaxTime":1205712000,"apparentTemperatureMin":37.27,"apparentTemperatureMinTime":1205676000,"apparentTemperatureMax":64.49,"apparentTemperatureMaxTime":1205712000},"2009":{"time":1237186800,"summary":"Drizzle in the morning.","icon":"rain","sunriseTime":1237213303,"sunsetTime":1237256454,"moonPhase":0.7,"precipIntensity":0.0025,"precipIntensityMax":0.008,"precipIntensityMaxTime":1237197600,"precipProbability":0.86,"precipType":"rain","temperatureHigh":57.82,"temperatureHighTime":1237233600,"temperatureLow":50.37,"temperatureLowTime":1237294800,"apparentTemperatureHigh":57.82,"apparentTemperatureHighTime":1237233600,"apparentTemperatureLow":50.37,"apparentTemperatureLowTime":1237294800,"dewPoint":51.33,"humidity":0.88,"pressure":1022.52,"windSpeed":5.16,"windGust":16.1,"windGustTime":1237240800,"windBearing":203,"cloudCover":0.99,"uvIndex":4,"uvIndexTime":1237233600,"visibility":7.384,"temperatureMin":52.47,"temperatureMinTime":1237186800,"temperatureMax":57.82,"temperatureMaxTime":1237233600,"apparentTemperatureMin":52.47,"apparentTemperatureMinTime":1237186800,"apparentTemperatureMax":57.82,"apparentTemperatureMaxTime":1237233600},"2010":{"time":1268722800,"summary":"Partly cloudy throughout the day.","icon":"clear-day","sunriseTime":1268749326,"sunsetTime":1268792440,"moonPhase":0.04,"precipIntensity":0,"precipIntensityMax":0,"precipProbability":0,"temperatureHigh":69.94,"temperatureHighTime":1268784000,"temperatureLow":47.5,"temperatureLowTime":1268838000,"apparentTemperatureHigh":69.94,"apparentTemperatureHighTime":1268784000,"apparentTemperatureLow":47.5,"apparentTemperatureLowTime":1268838000,"dewPoint":45.46,"humidity":0.68,"pressure":1023.47,"windSpeed":1.57,"windGust":7.31,"windGustTime":1268776800,"windBearing":251,"cloudCover":0.12,"uvIndex":6,"uvIndexTime":1268769600,"visibility":9.667,"temperatureMin":44.75,"temperatureMinTime":1268751600,"temperatureMax":69.94,"temperatureMaxTime":1268784000,"apparentTemperatureMin":44.75,"apparentTemperatureMinTime":1268751600,"apparentTemperatureMax":69.94,"apparentTemperatureMaxTime":1268784000},"2011":{"time":1300258800,"summary":"Drizzle in the morning.","icon":"rain","sunriseTime":1300285348,"sunsetTime":1300328426,"moonPhase":0.4,"precipIntensity":0.0037,"precipIntensityMax":0.0203,"precipIntensityMaxTime":1300269600,"precipProbability":0.94,"precipType":"rain","temperatureHigh":57.81,"temperatureHighTime":1300316400,"temperatureLow":37.61,"temperatureLowTime":1300374000,"apparentTemperatureHigh":57.81,"apparentTemperatureHighTime":1300316400,"apparentTemperatureLow":37.61,"apparentTemperatureLowTime":1300374000,"dewPoint":44.65,"humidity":0.77,"pressure":1021.09,"windSpeed":3.79,"windGust":11.99,"windGustTime":1300316400,"windBearing":259,"cloudCover":0.69,"uvIndex":4,"uvIndexTime":1300305600,"visibility":9.649,"temperatureMin":44.47,"temperatureMinTime":1300341600,"temperatureMax":57.81,"temperatureMaxTime":1300316400,"apparentTemperatureMin":44.47,"apparentTemperatureMinTime":1300341600,"apparentTemperatureMax":57.81,"apparentTemperatureMaxTime":1300316400},"2012":{"time":1331881200,"summary":"Rain until evening.","icon":"rain","sunriseTime":1331907677,"sunsetTime":1331950870,"moonPhase":0.82,"precipIntensity":0.0525,"precipIntensityMax":0.1133,"precipIntensityMaxTime":1331946000,"precipProbability":1,"precipType":"rain","temperatureHigh":54.56,"temperatureHighTime":1331938800,"temperatureLow":38.17,"temperatureLowTime":1331996400,"apparentTemperatureHigh":54.56,"apparentTemperatureHighTime":1331938800,"apparentTemperatureLow":38.17,"apparentTemperatureLowTime":1331996400,"dewPoint":49.51,"humidity":0.91,"pressure":1010.91,"windSpeed":3.9,"windGust":15.63,"windGustTime":1331946000,"windBearing":200,"cloudCover":0.99,"uvIndex":4,"uvIndexTime":1331928000,"visibility":4.854,"temperatureMin":46.04,"temperatureMinTime":1331964000,"temperatureMax":54.56,"temperatureMaxTime":1331938800,"apparentTemperatureMin":46.04,"apparentTemperatureMinTime":1331964000,"apparentTemperatureMax":54.56,"apparentTemperatureMaxTime":1331938800},"2013":{"time":1363417200,"summary":"Foggy in the morning.","icon":"partly-cloudy-day","sunriseTime":1363443700,"sunsetTime":1363486856,"moonPhase":0.17,"precipIntensity":0,"precipIntensityMax":0,"precipProbability":0,"temperatureHigh":74.14,"temperatureHighTime":1363474800,"temperatureLow":44.59,"temperatureLowTime":1363528800,"apparentTemperatureHigh":74.14,"apparentTemperatureHighTime":1363474800,"apparentTemperatureLow":44.59,"apparentTemperatureLowTime":1363528800,"dewPoint":41.96,"humidity":0.61,"pressure":1017.15,"windSpeed":2.77,"windGust":15.44,"windGustTime":1363474800,"windBearing":290,"cloudCover":0.22,"uvIndex":6,"uvIndexTime":1363464000,"visibility":9.386,"temperatureMin":43.15,"temperatureMinTime":1363446000,"temperatureMax":74.14,"temperatureMaxTime":1363474800,"apparentTemperatureMin":43.15,"apparentTemperatureMinTime":1363446000,"apparentTemperatureMax":74.14,"apparentTemperatureMaxTime":1363474800},"2014":{"time":1394953200,"summary":"Foggy in the morning.","icon":"partly-cloudy-day","sunriseTime":1394979723,"sunsetTime":1395022842,"moonPhase":0.51,"precipIntensity":0,"precipIntensityMax":0,"precipProbability":0,"temperatureHigh":75.93,"temperatureHighTime":1395003600,"temperatureLow":48.81,"temperatureLowTime":1395068400,"apparentTemperatureHigh":75.93,"apparentTemperatureHighTime":1395003600,"apparentTemperatureLow":48.81,"apparentTemperatureLowTime":1395068400,"dewPoint":42.88,"humidity":0.6,"pressure":1023.73,"windSpeed":1.78,"windGust":10.8,"windGustTime":1395014400,"windBearing":234,"cloudCover":0.33,"uvIndex":5,"uvIndexTime":1395000000,"visibility":8.603,"temperatureMin":44.53,"temperatureMinTime":1394982000,"temperatureMax":75.93,"temperatureMaxTime":1395003600,"apparentTemperatureMin":44.53,"apparentTemperatureMinTime":1394982000,"apparentTemperatureMax":75.93,"apparentTemperatureMaxTime":1395003600},"2015":{"time":1426489200,"summary":"Mostly cloudy throughout the day.","icon":"partly-cloudy-day","sunriseTime":1426515745,"sunsetTime":1426558828,"moonPhase":0.87,"precipIntensity":0,"precipIntensityMax":0,"precipProbability":0,"temperatureHigh":66.03,"temperatureHighTime":1426546800,"temperatureLow":48.24,"temperatureLowTime":1426604400,"apparentTemperatureHigh":66.03,"apparentTemperatureHighTime":1426546800,"apparentTemperatureLow":48.24,"apparentTemperatureLowTime":1426604400,"dewPoint":52.03,"humidity":0.76,"pressure":1016,"windSpeed":0.59,"windGust":4.56,"windGustTime":1426546800,"windBearing":202,"cloudCover":0.43,"uvIndex":4,"uvIndexTime":1426532400,"visibility":9.997,"temperatureMin":54.86,"temperatureMinTime":1426514400,"temperatureMax":66.03,"temperatureMaxTime":1426546800,"apparentTemperatureMin":54.86,"apparentTemperatureMinTime":1426514400,"apparentTemperatureMax":66.03,"apparentTemperatureMaxTime":1426546800},"2016":{"time":1458111600,"summary":"Partly cloudy throughout the day.","icon":"partly-cloudy-day","sunriseTime":1458138074,"sunsetTime":1458181272,"moonPhase":0.3,"precipIntensity":0,"precipIntensityMax":0,"precipProbability":0,"temperatureHigh":73.43,"temperatureHighTime":1458169200,"temperatureLow":46.87,"temperatureLowTime":1458226800,"apparentTemperatureHigh":73.43,"apparentTemperatureHighTime":1458169200,"apparentTemperatureLow":46.87,"apparentTemperatureLowTime":1458226800,"dewPoint":45.41,"humidity":0.67,"pressure":1017.73,"windSpeed":1.07,"windGust":6.95,"windGustTime":1458169200,"windBearing":248,"cloudCover":0.13,"uvIndex":5,"uvIndexTime":1458158400,"visibility":9.997,"temperatureMin":43.98,"temperatureMinTime":1458136800,"temperatureMax":73.43,"temperatureMaxTime":1458169200,"apparentTemperatureMin":43.98,"apparentTemperatureMinTime":1458136800,"apparentTemperatureMax":73.43,"apparentTemperatureMaxTime":1458169200},"2017":{"time":1489647600,"summary":"Mostly cloudy throughout the day.","icon":"partly-cloudy-day","sunriseTime":1489674097,"sunsetTime":1489717258,"moonPhase":0.64,"precipIntensity":0,"precipIntensityMax":0,"precipIntensityMaxTime":1489662000,"precipProbability":0,"temperatureHigh":68.83,"temperatureHighTime":1489698000,"temperatureLow":45.5,"temperatureLowTime":1489755600,"apparentTemperatureHigh":68.83,"apparentTemperatureHighTime":1489698000,"apparentTemperatureLow":45.5,"apparentTemperatureLowTime":1489755600,"dewPoint":51.29,"humidity":0.78,"pressure":1020.7,"windSpeed":1.18,"windGust":8.62,"windGustTime":1489701600,"windBearing":252,"cloudCover":0.58,"uvIndex":5,"uvIndexTime":1489694400,"visibility":9.685,"temperatureMin":51.98,"temperatureMinTime":1489730400,"temperatureMax":68.83,"temperatureMaxTime":1489698000,"apparentTemperatureMin":51.98,"apparentTemperatureMinTime":1489730400,"apparentTemperatureMax":68.83,"apparentTemperatureMaxTime":1489698000},"2018":{"time":1521183600,"summary":"Possible drizzle in the morning and afternoon.","icon":"rain","sunriseTime":1521210120,"sunsetTime":1521253244,"moonPhase":0.99,"precipIntensity":0.0036,"precipIntensityMax":0.0268,"precipIntensityMaxTime":1521183600,"precipProbability":0.87,"precipType":"rain","temperatureHigh":51.85,"temperatureHighTime":1521241200,"temperatureLow":38.23,"temperatureLowTime":1521277200,"apparentTemperatureHigh":51.85,"apparentTemperatureHighTime":1521241200,"apparentTemperatureLow":38.23,"apparentTemperatureLowTime":1521277200,"dewPoint":41.47,"humidity":0.84,"pressure":1011.03,"windSpeed":2.32,"windGust":13.96,"windGustTime":1521234000,"windBearing":271,"cloudCover":0.78,"uvIndex":4,"uvIndexTime":1521230400,"visibility":8.623,"temperatureMin":40.57,"temperatureMinTime":1521266400,"temperatureMax":51.85,"temperatureMaxTime":1521241200,"apparentTemperatureMin":40.57,"apparentTemperatureMinTime":1521266400,"apparentTemperatureMax":51.85,"apparentTemperatureMaxTime":1521241200},"2019":{"time":1552719600,"summary":"Partly cloudy throughout the day.","icon":"clear-day","sunriseTime":1552746142,"sunsetTime":1552789230,"moonPhase":0.35,"precipIntensity":0.0001,"precipIntensityMax":0.0011,"precipIntensityMaxTime":1552770000,"precipProbability":0.08,"precipType":"rain","temperatureHigh":72.67,"temperatureHighTime":1552777200,"temperatureLow":46.2,"temperatureLowTime":1552831200,"apparentTemperatureHigh":72.67,"apparentTemperatureHighTime":1552777200,"apparentTemperatureLow":46.2,"apparentTemperatureLowTime":1552831200,"dewPoint":35.33,"humidity":0.46,"pressure":1019.5,"windSpeed":3.74,"windGust":12.74,"windGustTime":1552777200,"windBearing":260,"cloudCover":0.06,"uvIndex":6,"uvIndexTime":1552766400,"visibility":9.756,"ozone":306,"temperatureMin":44.36,"temperatureMinTime":1552730400,"temperatureMax":72.67,"temperatureMaxTime":1552777200,"apparentTemperatureMin":41.64,"apparentTemperatureMinTime":1552730400,"apparentTemperatureMax":72.67,"apparentTemperatureMaxTime":1552777200}}