{"1944":{"time":-812826000,"summary":"Clear throughout the day.","icon":"clear-day","sunriseTime":-812800791,"sunsetTime":-812755564,"moonPhase":0.24,"precipType":"rain","temperatureHigh":71,"temperatureHighTime":-812772000,"temperatureLow":39.92,"temperatureLowTime":-812718000,"apparentTemperatureHigh":71,"apparentTemperatureHighTime":-812772000,"apparentTemperatureLow":37.74,"apparentTemperatureLowTime":-812714400,"dewPoint":42.21,"humidity":0.68,"pressure":1019.74,"windSpeed":4.22,"windBearing":177,"uvIndex":0,"uvIndexTime":-812826000,"temperatureMin":39.83,"temperatureMinTime":-812804400,"temperatureMax":71,"temperatureMaxTime":-812772000,"apparentTemperatureMin":37.24,"apparentTemperatureMinTime":-812804400,"apparentTemperatureMax":71,"apparentTemperatureMaxTime":-812772000},"1945":{"time":-781290000,"summary":"Clear throughout the day.","icon":"clear-day","sunriseTime":-781264769,"sunsetTime":-781219578,"moonPhase":0.57,"precipType":"rain","temperatureHigh":73.1,"temperatureHighTime":-781239600,"temperatureLow":41.05,"temperatureLowTime":-781178400,"apparentTemperatureHigh":73.1,"apparentTemperatureHighTime":-781239600,"apparentTemperatureLow":41.05,"apparentTemperatureLowTime":-781178400,"dewPoint":40.68,"humidity":0.5,"pressure":1021.62,"windSpeed":8.01,"windBearing":281,"uvIndex":0,"uvIndexTime":-781290000,"temperatureMin":48.16,"temperatureMinTime":-781207200,"temperatureMax":73.1,"temperatureMaxTime":-781239600,"apparentTemperatureMin":45.28,"apparentTemperatureMinTime":-781272000,"apparentTemperatureMax":73.1,"apparentTemperatureMaxTime":-781239600},"1946":{"time":-749750400,"summary":"Clear throughout the day.","icon":"clear-day","sunriseTime":-749728749,"sunsetTime":-749683588,"moonPhase":0.93,"temperatureHigh":59.05,"temperatureHighTime":-749696400,"apparentTemperatureHigh":59.05,"apparentTemperatureHighTime":-749696400,"dewPoint":41.76,"humidity":0.61,"pressure":1008.56,"windSpeed":16,"windBearing":150,"uvIndex":0,"uvIndexTime":-749750400,"temperatureMin":52.04,"temperatureMinTime":-749714400,"temperatureMax":59.05,"temperatureMaxTime":-749696400,"apparentTemperatureMin":52.04,"apparentTemperatureMinTime":-749714400,"apparentTemperatureMax":59.05,"apparentTemperatureMaxTime":-749696400},"1947":{},"1948":{},"1949":{},"1950":{},"1951":{},"1952":{},"1953":{},"1954":{},"1955":{},"1956":{},"1957":{},"1958":{},"1959":{},"1960":{},"1961":{},"1962":{},"1963":{},"1964":{},"1965":{},"1966":{},"1967":{},"1968":{},"1969":{},"1970":{},"1971":{},"1972":{},"1973":{"time":102326400,"summary":"Foggy in the morning and afternoon.","icon":"cloudy","sunriseTime":102348008,"sunsetTime":102393237,"moonPhase":0.88,"temperatureHigh":55.94,"temperatureHighTime":102369600,"temperatureLow":36.85,"temperatureLowTime":102438000,"apparentTemperatureHigh":55.94,"apparentTemperatureHighTime":102369600,"apparentTemperatureLow":36.85,"apparentTemperatureLowTime":102438000,"dewPoint":42.09,"humidity":0.71,"windSpeed":6.53,"windBearing":201,"cloudCover":0.89,"uvIndex":4,"uvIndexTime":102369600,"visibility":5.175,"temperatureMin":41.92,"temperatureMinTime":102409200,"temperatureMax":55.94,"temperatureMaxTime":102369600,"apparentTemperatureMin":41.92,"apparentTemperatureMinTime":102409200,"apparentTemperatureMax":55.94,"apparentTemperatureMaxTime":102369600},"1974":{"time":133858800,"summary":"Foggy in the morning.","icon":"partly-cloudy-day","sunriseTime":133884034,"sunsetTime":133929220,"moonPhase":0.25,"temperatureHigh":60.99,"temperatureHighTime":133912800,"temperatureLow":44.06,"temperatureLowTime":133974000,"apparentTemperatureHigh":60.99,"apparentTemperatureHighTime":133912800,"apparentTemperatureLow":40.6,"apparentTemperatureLowTime":133941600,"dewPoint":45.37,"humidity":0.73,"windSpeed":13.43,"windBearing":266,"cloudCover":0.64,"uvIndex":5,"uvIndexTime":133905600,"visibility":7.751,"temperatureMin":44.95,"temperatureMinTime":133941600,"temperatureMax":60.99,"temperatureMaxTime":133912800,"apparentTemperatureMin":40.6,"apparentTemperatureMinTime":133941600,"apparentTemperatureMax":60.99,"apparentTemperatureMaxTime":133912800},"1975":{"time":165394800,"summary":"Foggy in the morning.","icon":"clear-day","sunriseTime":165420056,"sunsetTime":165465207,"moonPhase":0.64,"temperatureHigh":66.02,"temperatureHighTime":165445200,"temperatureLow":44.95,"temperatureLowTime":165477600,"apparentTemperatureHigh":66.02,"apparentTemperatureHighTime":165445200,"apparentTemperatureLow":38.56,"apparentTemperatureLowTime":165506400,"dewPoint":44.54,"humidity":0.73,"windSpeed":7.05,"windBearing":153,"cloudCover":0.07,"uvIndex":7,"uvIndexTime":165441600,"visibility":8.972,"temperatureMin":35.97,"temperatureMinTime":165416400,"temperatureMax":66.02,"temperatureMaxTime":165445200,"apparentTemperatureMin":35.97,"apparentTemperatureMinTime":165416400,"apparentTemperatureMax":66.02,"apparentTemperatureMaxTime":165445200},"1976":{"time":197020800,"summary":"Partly cloudy throughout the day.","icon":"partly-cloudy-day","sunriseTime":197042382,"sunsetTime":197087652,"moonPhase":0.01,"windSpeed":9.46,"windBearing":158,"cloudCover":0.25,"uvIndex":6,"uvIndexTime":197067600,"visibility":8.786},"1977":{"time":228556800,"summary":"Partly cloudy throughout the day.","icon":"partly-cloudy-day","sunriseTime":228578405,"sunsetTime":228623639,"moonPhase":0.36,"windSpeed":7.41,"windBearing":285,"cloudCover":0.33,"uvIndex":6,"uvIndexTime":228600000,"visibility":9.647},"1978":{"time":260092800,"summary":"Overcast throughout the day.","icon":"cloudy","sunriseTime":260114427,"sunsetTime":260159625,"moonPhase":0.73,"temperatureHigh":69.09,"temperatureHighTime":260143200,"temperatureLow":64.94,"temperatureLowTime":260168400,"apparentTemperatureHigh":69.64,"apparentTemperatureHighTime":260157600,"apparentTemperatureLow":65.51,"apparentTemperatureLowTime":260172000,"dewPoint":56.7,"humidity":0.77,"windSpeed":5.7,"windBearing":142,"cloudCover":0.9,"uvIndex":5,"uvIndexTime":260139600,"visibility":8.823,"temperatureMin":53.06,"temperatureMinTime":260121600,"temperatureMax":69.09,"temperatureMaxTime":260143200,"apparentTemperatureMin":53.06,"apparentTemperatureMinTime":260121600,"apparentTemperatureMax":69.64,"apparentTemperatureMaxTime":260157600},"1979":{"time":291628800,"summary":"Clear throughout the day.","icon":"clear-day","sunriseTime":291650450,"sunsetTime":291695612,"moonPhase":0.11,"temperatureHigh":71.07,"temperatureHighTime":291690000,"apparentTemperatureHigh":71.07,"apparentTemperatureHighTime":291690000,"dewPoint":41.21,"humidity":0.6,"windSpeed":8.24,"windBearing":317,"cloudCover":0.04,"uvIndex":7,"uvIndexTime":291672000,"visibility":10,"temperatureMin":44.06,"temperatureMinTime":291650400,"temperatureMax":71.07,"temperatureMaxTime":291690000,"apparentTemperatureMin":41.51,"apparentTemperatureMinTime":291654000,"apparentTemperatureMax":71.07,"apparentTemperatureMaxTime":291690000},"1980":{"time":323251200,"summary":"Clear throughout the day.","icon":"clear-day","sunriseTime":323272779,"sunsetTime":323318054,"moonPhase":0.49,"temperatureHigh":66.92,"temperatureHighTime":323308800,"apparentTemperatureHigh":66.92,"apparentTemperatureHighTime":323308800,"dewPoint":33.69,"humidity":0.44,"windSpeed":15.13,"windBearing":336,"cloudCover":0.07,"uvIndex":8,"uvIndexTime":323294400,"visibility":10,"temperatureMin":48.02,"temperatureMinTime":323272800,"temperatureMax":66.92,"temperatureMaxTime":323308800,"apparentTemperatureMin":43.01,"apparentTemperatureMinTime":323305200,"apparentTemperatureMax":66.92,"apparentTemperatureMaxTime":323308800},"1981":{"time":354787200,"summary":"Partly cloudy throughout the day.","icon":"partly-cloudy-day","sunriseTime":354808802,"sunsetTime":354854040,"moonPhase":0.83,"temperatureHigh":66.92,"temperatureHighTime":354848400,"temperatureLow":39.92,"temperatureLowTime":354898800,"apparentTemperatureHigh":66.92,"apparentTemperatureHighTime":354848400,"apparentTemperatureLow":39.92,"apparentTemperatureLowTime":354898800,"dewPoint":43.3,"humidity":0.66,"windSpeed":8.33,"windBearing":282,"cloudCover":0.33,"uvIndex":7,"uvIndexTime":354834000,"visibility":9.999,"temperatureMin":42.07,"temperatureMinTime":354808800,"temperatureMax":66.92,"temperatureMaxTime":354848400,"apparentTemperatureMin":38.05,"apparentTemperatureMinTime":354812400,"apparentTemperatureMax":66.92,"apparentTemperatureMaxTime":354848400},"1982":{"time":386323200,"summary":"Foggy until evening.","icon":"fog","sunriseTime":386344825,"sunsetTime":386390027,"moonPhase":0.21,"temperatureHigh":51.99,"temperatureHighTime":386377200,"apparentTemperatureHigh":51.99,"apparentTemperatureHighTime":386377200,"dewPoint":48.44,"humidity":0.94,"windSpeed":15.51,"windBearing":178,"cloudCover":0.99,"uvIndex":4,"uvIndexTime":386366400,"visibility":1.999,"temperatureMin":46.05,"temperatureMinTime":386352000,"temperatureMax":51.99,"temperatureMaxTime":386377200,"apparentTemperatureMin":39.96,"apparentTemperatureMinTime":386352000,"apparentTemperatureMax":51.99,"apparentTemperatureMaxTime":386377200},"1983":{"time":417859200,"summary":"Foggy in the evening.","icon":"cloudy","sunriseTime":417880847,"sunsetTime":417926013,"moonPhase":0.59,"temperatureHigh":60.99,"temperatureHighTime":417902400,"apparentTemperatureHigh":60.99,"apparentTemperatureHighTime":417902400,"dewPoint":32.02,"humidity":0.36,"windSpeed":10.34,"windBearing":187,"cloudCover":0.94,"uvIndex":4,"uvIndexTime":417902400,"visibility":6.73,"temperatureMin":53.06,"temperatureMinTime":417884400,"temperatureMax":60.99,"temperatureMaxTime":417902400,"apparentTemperatureMin":53.06,"apparentTemperatureMinTime":417884400,"apparentTemperatureMax":60.99,"apparentTemperatureMaxTime":417902400},"1984":{"time":449481600,"summary":"Mostly cloudy throughout the day.","icon":"partly-cloudy-day","sunriseTime":449503176,"sunsetTime":449548456,"moonPhase":0.96,"temperatureHigh":66.92,"temperatureHighTime":449528400,"apparentTemperatureHigh":66.92,"apparentTemperatureHighTime":449528400,"dewPoint":43.35,"humidity":0.62,"windSpeed":10.7,"windBearing":211,"cloudCover":0.71,"uvIndex":6,"uvIndexTime":449521200,"visibility":10,"temperatureMin":42.98,"temperatureMinTime":449506800,"temperatureMax":66.92,"temperatureMaxTime":449528400,"apparentTemperatureMin":40.2,"apparentTemperatureMinTime":449506800,"apparentTemperatureMax":66.92,"apparentTemperatureMaxTime":449528400},"1985":{"time":481017600,"summary":"Partly cloudy throughout the day.","icon":"partly-cloudy-day","sunriseTime":481039199,"sunsetTime":481084442,"moonPhase":0.3,"temperatureHigh":69.98,"temperatureHighTime":481068000,"apparentTemperatureHigh":69.98,"apparentTemperatureHighTime":481068000,"dewPoint":50.4,"humidity":0.63,"windSpeed":9.42,"windBearing":256,"cloudCover":0.18,"uvIndex":7,"uvIndexTime":481057200,"visibility":10,"temperatureMin":46.94,"temperatureMinTime":481046400,"temperatureMax":69.98,"temperatureMaxTime":481068000,"apparentTemperatureMin":46.94,"apparentTemperatureMinTime":481046400,"apparentTemperatureMax":69.98,"apparentTemperatureMaxTime":481068000},"1986":{"time":512553600,"summary":"Mostly cloudy throughout the day.","icon":"partly-cloudy-day","sunriseTime":512575222,"sunsetTime":512620429,"moonPhase":0.69,"temperatureHigh":66.02,"temperatureHighTime":512607600,"temperatureLow":53.97,"temperatureLowTime":512629200,"apparentTemperatureHigh":66.02,"apparentTemperatureHighTime":512607600,"apparentTemperatureLow":53.97,"apparentTemperatureLowTime":512629200,"dewPoint":54.8,"humidity":0.82,"windSpeed":6.14,"windBearing":157,"cloudCover":0.67,"uvIndex":4,"uvIndexTime":512596800,"visibility":5.967,"temperatureMin":53.97,"temperatureMinTime":512629200,"temperatureMax":66.02,"temperatureMaxTime":512607600,"apparentTemperatureMin":53.97,"apparentTemperatureMinTime":512629200,"apparentTemperatureMax":66.02,"apparentTemperatureMaxTime":512607600},"1987":{"time":544089600,"summary":"Mostly cloudy throughout the day.","icon":"partly-cloudy-day","sunriseTime":544111244,"sunsetTime":544156415,"moonPhase":0.06,"temperatureHigh":78.1,"temperatureHighTime":544140000,"apparentTemperatureHigh":78.1,"apparentTemperatureHighTime":544140000,"dewPoint":42.92,"humidity":0.47,"windSpeed":6.96,"windBearing":159,"cloudCover":0.81,"uvIndex":4,"uvIndexTime":544136400,"visibility":10,"temperatureMin":44.06,"temperatureMinTime":544114800,"temperatureMax":78.1,"temperatureMaxTime":544140000,"apparentTemperatureMin":39.75,"apparentTemperatureMinTime":544114800,"apparentTemperatureMax":78.1,"apparentTemperatureMaxTime":544140000},"1988":{"time":575712000,"summary":"Partly cloudy throughout the day.","icon":"partly-cloudy-day","sunriseTime":575733573,"sunsetTime":575778858,"moonPhase":0.43,"temperatureHigh":71.07,"temperatureHighTime":575766000,"apparentTemperatureHigh":71.07,"apparentTemperatureHighTime":575766000,"dewPoint":30.68,"humidity":0.37,"windSpeed":12.29,"windBearing":347,"cloudCover":0.27,"uvIndex":7,"uvIndexTime":575755200,"visibility":10,"temperatureMin":44.06,"temperatureMinTime":575737200,"temperatureMax":71.07,"temperatureMaxTime":575766000,"apparentTemperatureMin":38.15,"apparentTemperatureMinTime":575737200,"apparentTemperatureMax":71.07,"apparentTemperatureMaxTime":575766000},"1989":{"time":607248000,"summary":"Foggy in the morning.","icon":"partly-cloudy-day","sunriseTime":607269596,"sunsetTime":607314844,"moonPhase":0.78,"temperatureHigh":68,"temperatureHighTime":607302000,"apparentTemperatureHigh":68,"apparentTemperatureHighTime":607302000,"dewPoint":47.33,"humidity":0.72,"windSpeed":6.39,"windBearing":164,"cloudCover":0.72,"uvIndex":7,"uvIndexTime":607291200,"visibility":8.353,"temperatureMin":39.01,"temperatureMinTime":607273200,"temperatureMax":68,"temperatureMaxTime":607302000,"apparentTemperatureMin":39.01,"apparentTemperatureMinTime":607273200,"apparentTemperatureMax":68,"apparentTemperatureMaxTime":607302000},"1990":{"time":638784000,"summary":"Mostly cloudy throughout the day.","icon":"partly-cloudy-day","sunriseTime":638805619,"sunsetTime":638850830,"moonPhase":0.17,"temperatureHigh":62.96,"temperatureHighTime":638834400,"apparentTemperatureHigh":62.96,"apparentTemperatureHighTime":638834400,"dewPoint":48.34,"humidity":0.82,"windSpeed":7.97,"windBearing":165,"cloudCover":0.3,"uvIndex":7,"uvIndexTime":638830800,"visibility":6.429,"temperatureMin":46.05,"temperatureMinTime":638856000,"temperatureMax":62.96,"temperatureMaxTime":638834400,"apparentTemperatureMin":42.46,"apparentTemperatureMinTime":638856000,"apparentTemperatureMax":62.96,"apparentTemperatureMaxTime":638834400},"1991":{"time":670320000,"summary":"Foggy in the morning.","icon":"partly-cloudy-day","sunriseTime":670341641,"sunsetTime":670386817,"moonPhase":0.53,"temperatureHigh":69.98,"temperatureHighTime":670366800,"apparentTemperatureHigh":69.98,"apparentTemperatureHighTime":670366800,"dewPoint":51.4,"humidity":0.71,"windSpeed":7.48,"windBearing":169,"cloudCover":0.2,"uvIndex":7,"uvIndexTime":670363200,"visibility":6.964,"temperatureMin":44.06,"temperatureMinTime":670348800,"temperatureMax":69.98,"temperatureMaxTime":670366800,"apparentTemperatureMin":44.06,"apparentTemperatureMinTime":670348800,"apparentTemperatureMax":69.98,"apparentTemperatureMaxTime":670366800},"1992":{"time":701942400,"summary":"Overcast throughout the day.","icon":"cloudy","sunriseTime":701963970,"sunsetTime":702009259,"moonPhase":0.9,"temperatureHigh":55.94,"temperatureHighTime":701996400,"apparentTemperatureHigh":55.94,"apparentTemperatureHighTime":701996400,"dewPoint":47.37,"humidity":0.83,"windSpeed":11.51,"windBearing":319,"cloudCover":0.96,"uvIndex":5,"uvIndexTime":701985600,"visibility":9.142,"temperatureMin":48.02,"temperatureMinTime":701971200,"temperatureMax":55.94,"temperatureMaxTime":701996400,"apparentTemperatureMin":42.4,"apparentTemperatureMinTime":701971200,"apparentTemperatureMax":55.94,"apparentTemperatureMaxTime":701996400},"1993":{"time":733478400,"summary":"Mostly cloudy throughout the day.","icon":"partly-cloudy-day","sunriseTime":733499993,"sunsetTime":733545246,"moonPhase":0.25,"temperatureHigh":68,"temperatureHighTime":733532400,"apparentTemperatureHigh":68,"apparentTemperatureHighTime":733532400,"dewPoint":48.69,"humidity":0.68,"windSpeed":4.42,"windBearing":163,"cloudCover":0.84,"uvIndex":5,"uvIndexTime":733521600,"visibility":9.615,"temperatureMin":44.95,"temperatureMinTime":733503600,"temperatureMax":68,"temperatureMaxTime":733532400,"apparentTemperatureMin":44.95,"apparentTemperatureMinTime":733503600,"apparentTemperatureMax":68,"apparentTemperatureMaxTime":733532400},"1994":{"time":765014400,"summary":"Foggy in the morning.","icon":"partly-cloudy-day","sunriseTime":765036016,"sunsetTime":765081232,"moonPhase":0.64,"temperatureHigh":66.92,"temperatureHighTime":765072000,"apparentTemperatureHigh":66.92,"apparentTemperatureHighTime":765072000,"dewPoint":44.47,"humidity":0.62,"windSpeed":7.1,"windBearing":221,"cloudCover":0.29,"uvIndex":7,"uvIndexTime":765057600,"visibility":8.105,"temperatureMin":45.86,"temperatureMinTime":765039600,"temperatureMax":66.92,"temperatureMaxTime":765072000,"apparentTemperatureMin":45.86,"apparentTemperatureMinTime":765039600,"apparentTemperatureMax":66.92,"apparentTemperatureMaxTime":765072000},"1995":{"time":796550400,"summary":"Mostly cloudy throughout the day.","icon":"partly-cloudy-day","sunriseTime":796572038,"sunsetTime":796617218,"moonPhase":0,"temperatureHigh":72.85,"temperatureHighTime":796604400,"temperatureLow":38.84,"temperatureLowTime":796662000,"apparentTemperatureHigh":72.85,"apparentTemperatureHighTime":796604400,"apparentTemperatureLow":38.84,"apparentTemperatureLowTime":796662000,"dewPoint":41,"humidity":0.49,"windSpeed":4.28,"windBearing":151,"cloudCover":0.69,"uvIndex":5,"uvIndexTime":796593600,"visibility":10,"temperatureMin":41,"temperatureMinTime":796575600,"temperatureMax":72.85,"temperatureMaxTime":796604400,"apparentTemperatureMin":41,"apparentTemperatureMinTime":796575600,"apparentTemperatureMax":72.85,"apparentTemperatureMaxTime":796604400},"1996":{"time":828172800,"summary":"Partly cloudy throughout the day.","icon":"partly-cloudy-day","sunriseTime":828194367,"sunsetTime":828239661,"moonPhase":0.38,"temperatureHigh":64.94,"temperatureHighTime":828226800,"apparentTemperatureHigh":64.94,"apparentTemperatureHighTime":828226800,"dewPoint":42.4,"humidity":0.63,"windSpeed":6.21,"windBearing":157,"cloudCover":0.45,"uvIndex":7,"uvIndexTime":828216000,"visibility":9,"temperatureMin":41.92,"temperatureMinTime":828198000,"temperatureMax":64.94,"temperatureMaxTime":828226800,"apparentTemperatureMin":41.92,"apparentTemperatureMinTime":828198000,"apparentTemperatureMax":64.94,"apparentTemperatureMaxTime":828226800},"1997":{"time":859708800,"summary":"Foggy in the afternoon.","icon":"partly-cloudy-day","sunriseTime":859730390,"sunsetTime":859775647,"moonPhase":0.73,"temperatureHigh":59,"temperatureHighTime":859752000,"apparentTemperatureHigh":59,"apparentTemperatureHighTime":859752000,"dewPoint":45.11,"humidity":0.77,"windSpeed":7.54,"windBearing":204,"cloudCover":0.8,"uvIndex":5,"uvIndexTime":859755600,"visibility":6.929,"temperatureMin":46.41,"temperatureMinTime":859734000,"temperatureMax":59,"temperatureMaxTime":859752000,"apparentTemperatureMin":42.37,"apparentTemperatureMinTime":859780800,"apparentTemperatureMax":59,"apparentTemperatureMaxTime":859752000},"1998":{"time":891244800,"summary":"Mostly cloudy throughout the day.","icon":"partly-cloudy-day","sunriseTime":891266413,"sunsetTime":891311634,"moonPhase":0.12,"temperatureHigh":62.6,"temperatureHighTime":891295200,"apparentTemperatureHigh":62.6,"apparentTemperatureHighTime":891295200,"dewPoint":40.58,"humidity":0.63,"windSpeed":8.04,"windBearing":170,"cloudCover":0.53,"uvIndex":7,"uvIndexTime":891284400,"visibility":10,"temperatureMin":37.4,"temperatureMinTime":891270000,"temperatureMax":62.6,"temperatureMaxTime":891295200,"apparentTemperatureMin":37.4,"apparentTemperatureMinTime":891270000,"apparentTemperatureMax":62.6,"apparentTemperatureMaxTime":891295200},"1999":{"time":922780800,"summary":"Rain in the afternoon and evening.","icon":"partly-cloudy-day","sunriseTime":922802435,"sunsetTime":922847620,"moonPhase":0.48,"precipIntensity":0.0424,"precipIntensityMax":0.2007,"precipIntensityMaxTime":922845600,"precipProbability":1,"temperatureHigh":51.79,"temperatureHighTime":922827600,"temperatureLow":32.02,"temperatureLowTime":922892400,"apparentTemperatureHigh":51.79,"apparentTemperatureHighTime":922827600,"apparentTemperatureLow":27.4,"apparentTemperatureLowTime":922892400,"dewPoint":38.02,"humidity":0.83,"pressure":1016.08,"windSpeed":4.77,"windBearing":220,"cloudCover":0.66,"uvIndex":4,"uvIndexTime":922827600,"visibility":8.237,"temperatureMin":33.78,"temperatureMinTime":922798800,"temperatureMax":51.79,"temperatureMaxTime":922827600,"apparentTemperatureMin":33.78,"apparentTemperatureMinTime":922798800,"apparentTemperatureMax":51.79,"apparentTemperatureMaxTime":922827600},"2000":{"time":954403200,"summary":"Clear throughout the day.","icon":"clear-day","sunriseTime":954424764,"sunsetTime":954470063,"moonPhase":0.85,"precipType":"rain","temperatureHigh":80.55,"temperatureHighTime":954460800,"temperatureLow":53.56,"temperatureLowTime":954504000,"apparentTemperatureHigh":80.55,"apparentTemperatureHighTime":954460800,"apparentTemperatureLow":53.56,"apparentTemperatureLowTime":954504000,"dewPoint":36.96,"humidity":0.53,"pressure":1018.86,"windSpeed":6.46,"windBearing":341,"cloudCover":0,"uvIndex":8,"uvIndexTime":954446400,"visibility":9.649,"temperatureMin":39.18,"temperatureMinTime":954417600,"temperatureMax":80.55,"temperatureMaxTime":954460800,"apparentTemperatureMin":33.57,"apparentTemperatureMinTime":954417600,"apparentTemperatureMax":80.55,"apparentTemperatureMaxTime":954460800},"2001":{"time":985939200,"summary":"Clear throughout the day.","icon":"clear-day","sunriseTime":985960787,"sunsetTime":986006049,"moonPhase":0.21,"precipType":"rain","temperatureHigh":80.92,"temperatureHighTime":985996800,"temperatureLow":46.9,"temperatureLowTime":986047200,"apparentTemperatureHigh":80.92,"apparentTemperatureHighTime":985996800,"apparentTemperatureLow":46.9,"apparentTemperatureLowTime":986047200,"dewPoint":47.08,"humidity":0.62,"pressure":1014.2,"windSpeed":5.7,"windBearing":332,"cloudCover":0,"uvIndex":8,"uvIndexTime":985982400,"visibility":8.498,"temperatureMin":46.9,"temperatureMinTime":985957200,"temperatureMax":80.92,"temperatureMaxTime":985996800,"apparentTemperatureMin":44.08,"apparentTemperatureMinTime":985957200,"apparentTemperatureMax":80.92,"apparentTemperatureMaxTime":985996800},"2002":{"time":1017475200,"summary":"Foggy in the morning and overnight.","icon":"partly-cloudy-day","sunriseTime":1017496810,"sunsetTime":1017542035,"moonPhase":0.59,"precipType":"rain","temperatureHigh":80.81,"temperatureHighTime":1017525600,"temperatureLow":44.56,"temperatureLowTime":1017576000,"apparentTemperatureHigh":80.95,"apparentTemperatureHighTime":1017525600,"apparentTemperatureLow":44.56,"apparentTemperatureLowTime":1017576000,"dewPoint":45.83,"humidity":0.63,"pressure":1017.23,"windSpeed":2.61,"windGust":10.01,"windGustTime":1017532800,"windBearing":129,"cloudCover":0.48,"uvIndex":8,"uvIndexTime":1017518400,"visibility":5.187,"temperatureMin":47.54,"temperatureMinTime":1017493200,"temperatureMax":80.81,"temperatureMaxTime":1017525600,"apparentTemperatureMin":47.54,"apparentTemperatureMinTime":1017493200,"apparentTemperatureMax":80.95,"apparentTemperatureMaxTime":1017525600},"2003":{"time":1049011200,"summary":"Clear throughout the day.","icon":"clear-day","sunriseTime":1049032832,"sunsetTime":1049078022,"moonPhase":0.95,"precipType":"rain","temperatureHigh":79.77,"temperatureHighTime":1049065200,"temperatureLow":48.52,"temperatureLowTime":1049119200,"apparentTemperatureHigh":79.77,"apparentTemperatureHighTime":1049065200,"apparentTemperatureLow":48.52,"apparentTemperatureLowTime":1049119200,"dewPoint":44.44,"humidity":0.57,"pressure":1023.28,"windSpeed":1.1,"windGust":8.37,"windGustTime":1049065200,"windBearing":208,"cloudCover":0,"uvIndex":7,"uvIndexTime":1049054400,"visibility":9.997,"temperatureMin":46.88,"temperatureMinTime":1049032800,"temperatureMax":79.77,"temperatureMaxTime":1049065200,"apparentTemperatureMin":46.88,"apparentTemperatureMinTime":1049032800,"apparentTemperatureMax":79.77,"apparentTemperatureMaxTime":1049065200},"2004":{"time":1080633600,"summary":"Mostly cloudy throughout the day.","icon":"partly-cloudy-day","sunriseTime":1080655162,"sunsetTime":1080700464,"moonPhase":0.32,"precipIntensity":0.0001,"precipIntensityMax":0.0014,"precipIntensityMaxTime":1080680400,"precipProbability":0.22,"precipType":"rain","temperatureHigh":64.89,"temperatureHighTime":1080687600,"temperatureLow":45.29,"temperatureLowTime":1080741600,"apparentTemperatureHigh":64.89,"apparentTemperatureHighTime":1080687600,"apparentTemperatureLow":44.28,"apparentTemperatureLowTime":1080734400,"dewPoint":44.06,"humidity":0.68,"pressure":1015.12,"windSpeed":4.3,"windGust":13.83,"windGustTime":1080691200,"windBearing":292,"cloudCover":0.3,"uvIndex":8,"uvIndexTime":1080676800,"visibility":9.997,"temperatureMin":49.09,"temperatureMinTime":1080716400,"temperatureMax":64.89,"temperatureMaxTime":1080687600,"apparentTemperatureMin":48.55,"apparentTemperatureMinTime":1080716400,"apparentTemperatureMax":64.89,"apparentTemperatureMaxTime":1080687600},"2005":{"time":1112169600,"summary":"Clear throughout the day.","icon":"clear-day","sunriseTime":1112191184,"sunsetTime":1112236451,"moonPhase":0.68,"precipIntensity":0,"precipIntensityMax":0,"precipProbability":0,"temperatureHigh":68.38,"temperatureHighTime":1112220000,"temperatureLow":42.82,"temperatureLowTime":1112274000,"apparentTemperatureHigh":68.38,"apparentTemperatureHighTime":1112220000,"apparentTemperatureLow":42.82,"apparentTemperatureLowTime":1112274000,"dewPoint":37.63,"humidity":0.56,"pressure":1023.9,"windSpeed":3.22,"windGust":10.79,"windGustTime":1112169600,"windBearing":330,"cloudCover":0,"uvIndex":8,"uvIndexTime":1112212800,"visibility":9.997,"temperatureMin":41,"temperatureMinTime":1112191200,"temperatureMax":68.38,"temperatureMaxTime":1112220000,"apparentTemperatureMin":38.86,"apparentTemperatureMinTime":1112191200,"apparentTemperatureMax":68.38,"apparentTemperatureMaxTime":1112220000},"2006":{"time":1143705600,"summary":"Drizzle starting in the afternoon.","icon":"rain","sunriseTime":1143727207,"sunsetTime":1143772437,"moonPhase":0.07,"precipIntensity":0.0029,"precipIntensityMax":0.0139,"precipIntensityMaxTime":1143756000,"precipProbability":0.9,"precipType":"rain","temperatureHigh":54.86,"temperatureHighTime":1143748800,"temperatureLow":48.28,"temperatureLowTime":1143802800,"apparentTemperatureHigh":54.86,"apparentTemperatureHighTime":1143748800,"apparentTemperatureLow":46.53,"apparentTemperatureLowTime":1143810000,"dewPoint":47.21,"humidity":0.87,"pressure":1014.86,"windSpeed":2.72,"windGust":9.67,"windGustTime":1143748800,"windBearing":158,"cloudCover":0.99,"uvIndex":4,"uvIndexTime":1143748800,"visibility":8.456,"temperatureMin":49,"temperatureMinTime":1143788400,"temperatureMax":54.86,"temperatureMaxTime":1143748800,"apparentTemperatureMin":48.92,"apparentTemperatureMinTime":1143781200,"apparentTemperatureMax":54.86,"apparentTemperatureMaxTime":1143748800},"2007":{"time":1175238000,"summary":"Foggy in the morning and overnight.","icon":"partly-cloudy-day","sunriseTime":1175263233,"sunsetTime":1175308420,"moonPhase":0.42,"precipIntensity":0,"precipIntensityMax":0,"precipProbability":0,"temperatureHigh":72.04,"temperatureHighTime":1175295600,"temperatureLow":41.17,"temperatureLowTime":1175342400,"apparentTemperatureHigh":72.04,"apparentTemperatureHighTime":1175295600,"apparentTemperatureLow":41.17,"apparentTemperatureLowTime":1175342400,"dewPoint":42.19,"humidity":0.66,"pressure":1019.53,"windSpeed":2.18,"windGust":10.19,"windGustTime":1175299200,"windBearing":189,"cloudCover":0.27,"uvIndex":7,"uvIndexTime":1175284800,"visibility":8.443,"temperatureMin":41.44,"temperatureMinTime":1175259600,"temperatureMax":72.04,"temperatureMaxTime":1175295600,"apparentTemperatureMin":41.44,"apparentTemperatureMinTime":1175259600,"apparentTemperatureMax":72.04,"apparentTemperatureMaxTime":1175295600},"2008":{"time":1206860400,"summary":"Partly cloudy throughout the day.","icon":"partly-cloudy-day","sunriseTime":1206885562,"sunsetTime":1206930863,"moonPhase":0.79,"precipIntensity":0,"precipIntensityMax":0,"precipProbability":0,"temperatureHigh":59.37,"temperatureHighTime":1206914400,"temperatureLow":33.07,"temperatureLowTime":1206972000,"apparentTemperatureHigh":59.37,"apparentTemperatureHighTime":1206914400,"apparentTemperatureLow":33.07,"apparentTemperatureLowTime":1206972000,"dewPoint":33.2,"humidity":0.6,"pressure":1015.77,"windSpeed":4.46,"windGust":16.38,"windGustTime":1206910800,"windBearing":301,"cloudCover":0.25,"uvIndex":8,"uvIndexTime":1206907200,"visibility":9.997,"temperatureMin":39.02,"temperatureMinTime":1206885600,"temperatureMax":59.37,"temperatureMaxTime":1206914400,"apparentTemperatureMin":39.02,"apparentTemperatureMinTime":1206885600,"apparentTemperatureMax":59.37,"apparentTemperatureMaxTime":1206914400},"2009":{"time":1238396400,"summary":"Clear throughout the day.","icon":"clear-day","sunriseTime":1238421584,"sunsetTime":1238466849,"moonPhase":0.16,"precipIntensity":0,"precipIntensityMax":0,"precipProbability":0,"temperatureHigh":70.68,"temperatureHighTime":1238450400,"temperatureLow":41.24,"temperatureLowTime":1238504400,"apparentTemperatureHigh":70.68,"apparentTemperatureHighTime":1238450400,"apparentTemperatureLow":41.24,"apparentTemperatureLowTime":1238504400,"dewPoint":31.62,"humidity":0.43,"pressure":1017.85,"windSpeed":5.13,"windGust":13.57,"windGustTime":1238436000,"windBearing":322,"cloudCover":0,"uvIndex":8,"uvIndexTime":1238443200,"visibility":9.997,"temperatureMin":44.82,"temperatureMinTime":1238421600,"temperatureMax":70.68,"temperatureMaxTime":1238450400,"apparentTemperatureMin":42.12,"apparentTemperatureMinTime":1238421600,"apparentTemperatureMax":70.68,"apparentTemperatureMaxTime":1238450400},"2010":{"time":1269932400,"summary":"Light rain until morning, starting again in the evening.","icon":"rain","sunriseTime":1269957607,"sunsetTime":1270002836,"moonPhase":0.54,"precipIntensity":0.0074,"precipIntensityMax":0.0347,"precipIntensityMaxTime":1269950400,"precipProbability":0.92,"precipType":"rain","temperatureHigh":55.11,"temperatureHighTime":1269982800,"temperatureLow":38.98,"temperatureLowTime":1270044000,"apparentTemperatureHigh":55.11,"apparentTemperatureHighTime":1269982800,"apparentTemperatureLow":38.98,"apparentTemperatureLowTime":1270044000,"dewPoint":43.14,"humidity":0.77,"pressure":1010.63,"windSpeed":5.49,"windGust":15.77,"windGustTime":1269990000,"windBearing":242,"cloudCover":0.84,"uvIndex":5,"uvIndexTime":1269979200,"visibility":9.607,"temperatureMin":43.64,"temperatureMinTime":1270015200,"temperatureMax":55.11,"temperatureMaxTime":1269982800,"apparentTemperatureMin":43.64,"apparentTemperatureMinTime":1270015200,"apparentTemperatureMax":55.11,"apparentTemperatureMaxTime":1269982800},"2011":{"time":1301468400,"summary":"Partly cloudy throughout the day.","icon":"partly-cloudy-day","sunriseTime":1301493630,"sunsetTime":1301538822,"moonPhase":0.9,"precipIntensity":0,"precipIntensityMax":0,"precipProbability":0,"temperatureHigh":82.22,"temperatureHighTime":1301529600,"temperatureLow":52.18,"temperatureLowTime":1301580000,"apparentTemperatureHigh":82.22,"apparentTemperatureHighTime":1301529600,"apparentTemperatureLow":52.18,"apparentTemperatureLowTime":1301580000,"dewPoint":50.14,"humidity":0.63,"pressure":1022.33,"windSpeed":3.34,"windGust":8.96,"windGustTime":1301522400,"windBearing":322,"cloudCover":0.23,"uvIndex":6,"uvIndexTime":1301515200,"visibility":9.957,"temperatureMin":50.22,"temperatureMinTime":1301486400,"temperatureMax":82.22,"temperatureMaxTime":1301529600,"apparentTemperatureMin":50.22,"apparentTemperatureMinTime":1301486400,"apparentTemperatureMax":82.22,"apparentTemperatureMaxTime":1301529600},"2012":{"time":1333090800,"summary":"Possible drizzle in the morning and afternoon.","icon":"rain","sunriseTime":1333115959,"sunsetTime":1333161265,"moonPhase":0.26,"precipIntensity":0.0016,"precipIntensityMax":0.0051,"precipIntensityMaxTime":1333126800,"precipProbability":0.6,"precipType":"rain","temperatureHigh":58.06,"temperatureHighTime":1333148400,"temperatureLow":50.38,"temperatureLowTime":1333206000,"apparentTemperatureHigh":58.06,"apparentTemperatureHighTime":1333148400,"apparentTemperatureLow":50.38,"apparentTemperatureLowTime":1333206000,"dewPoint":52,"humidity":0.89,"pressure":1015.2,"windSpeed":3.3,"windGust":10.46,"windGustTime":1333152000,"windBearing":181,"cloudCover":0.99,"uvIndex":4,"uvIndexTime":1333137600,"visibility":7.014,"temperatureMin":53.17,"temperatureMinTime":1333090800,"temperatureMax":58.06,"temperatureMaxTime":1333148400,"apparentTemperatureMin":53.17,"apparentTemperatureMinTime":1333090800,"apparentTemperatureMax":58.06,"apparentTemperatureMaxTime":1333148400},"2013":{"time":1364626800,"summary":"Light rain throughout the day.","icon":"rain","sunriseTime":1364651981,"sunsetTime":1364697251,"moonPhase":0.64,"precipIntensity":0.0024,"precipIntensityMax":0.0211,"precipIntensityMaxTime":1364702400,"precipProbability":0.96,"precipType":"rain","temperatureHigh":64.95,"temperatureHighTime":1364684400,"temperatureLow":53.23,"temperatureLowTime":1364738400,"apparentTemperatureHigh":64.95,"apparentTemperatureHighTime":1364684400,"apparentTemperatureLow":53.23,"apparentTemperatureLowTime":1364738400,"dewPoint":50.6,"humidity":0.81,"pressure":1016.63,"windSpeed":1.47,"windGust":7.95,"windGustTime":1364688000,"windBearing":214,"cloudCover":0.76,"uvIndex":6,"uvIndexTime":1364680800,"visibility":9.331,"temperatureMin":51.37,"temperatureMinTime":1364652000,"temperatureMax":64.95,"temperatureMaxTime":1364684400,"apparentTemperatureMin":51.37,"apparentTemperatureMinTime":1364652000,"apparentTemperatureMax":64.95,"apparentTemperatureMaxTime":1364684400},"2014":{"time":1396162800,"summary":"Foggy in the morning.","icon":"partly-cloudy-day","sunriseTime":1396188004,"sunsetTime":1396233237,"moonPhase":0.01,"precipIntensity":0,"precipIntensityMax":0,"precipIntensityMaxTime":1396198800,"precipProbability":0,"temperatureHigh":60.1,"temperatureHighTime":1396213200,"temperatureLow":43.35,"temperatureLowTime":1396260000,"apparentTemperatureHigh":60.1,"apparentTemperatureHighTime":1396213200,"apparentTemperatureLow":43.35,"apparentTemperatureLowTime":1396260000,"dewPoint":42.5,"humidity":0.75,"pressure":1017.81,"windSpeed":2.02,"windGust":12.57,"windGustTime":1396224000,"windBearing":258,"cloudCover":0.51,"uvIndex":7,"uvIndexTime":1396213200,"visibility":9.445,"temperatureMin":42.74,"temperatureMinTime":1396188000,"temperatureMax":60.1,"temperatureMaxTime":1396213200,"apparentTemperatureMin":42.74,"apparentTemperatureMinTime":1396188000,"apparentTemperatureMax":60.1,"apparentTemperatureMaxTime":1396213200},"2015":{"time":1427698800,"summary":"Partly cloudy throughout the day.","icon":"partly-cloudy-day","sunriseTime":1427724027,"sunsetTime":1427769224,"moonPhase":0.37,"precipIntensity":0,"precipIntensityMax":0,"precipProbability":0,"temperatureHigh":75.66,"temperatureHighTime":1427749200,"temperatureLow":50.41,"temperatureLowTime":1427803200,"apparentTemperatureHigh":75.66,"apparentTemperatureHighTime":1427749200,"apparentTemperatureLow":50.41,"apparentTemperatureLowTime":1427803200,"dewPoint":48.08,"humidity":0.65,"pressure":1015.76,"windSpeed":1.78,"windGust":9.97,"windGustTime":1427756400,"windBearing":243,"cloudCover":0.27,"uvIndex":6,"uvIndexTime":1427745600,"visibility":9.858,"temperatureMin":48.89,"temperatureMinTime":1427724000,"temperatureMax":75.66,"temperatureMaxTime":1427749200,"apparentTemperatureMin":48.89,"apparentTemperatureMinTime":1427724000,"apparentTemperatureMax":75.66,"apparentTemperatureMaxTime":1427749200},"2016":{"time":1459321200,"summary":"Foggy in the morning.","icon":"partly-cloudy-day","sunriseTime":1459346356,"sunsetTime":1459391666,"moonPhase":0.73,"precipIntensity":0,"precipIntensityMax":0,"precipProbability":0,"temperatureHigh":65.15,"temperatureHighTime":1459371600,"temperatureLow":47.31,"temperatureLowTime":1459425600,"apparentTemperatureHigh":65.15,"apparentTemperatureHighTime":1459371600,"apparentTemperatureLow":47.31,"apparentTemperatureLowTime":1459425600,"dewPoint":43.85,"humidity":0.73,"pressure":1014.15,"windSpeed":1.59,"windGust":9.82,"windGustTime":1459375200,"windBearing":217,"cloudCover":0.44,"uvIndex":7,"uvIndexTime":1459368000,"visibility":8.613,"temperatureMin":43.65,"temperatureMinTime":1459346400,"temperatureMax":65.15,"temperatureMaxTime":1459371600,"apparentTemperatureMin":43.65,"apparentTemperatureMinTime":1459346400,"apparentTemperatureMax":65.15,"apparentTemperatureMaxTime":1459371600},"2017":{"time":1490857200,"summary":"Partly cloudy throughout the day.","icon":"partly-cloudy-day","sunriseTime":1490882379,"sunsetTime":1490927653,"moonPhase":0.12,"precipIntensity":0,"precipIntensityMax":0.0004,"precipIntensityMaxTime":1490868000,"precipProbability":0.06,"temperatureHigh":67.32,"temperatureHighTime":1490914800,"temperatureLow":45.77,"temperatureLowTime":1490968800,"apparentTemperatureHigh":67.32,"apparentTemperatureHighTime":1490914800,"apparentTemperatureLow":45.77,"apparentTemperatureLowTime":1490968800,"dewPoint":42.98,"humidity":0.6,"pressure":1017.74,"windSpeed":5.26,"windGust":15.84,"windGustTime":1490889600,"windBearing":308,"cloudCover":0.31,"uvIndex":8,"uvIndexTime":1490904000,"visibility":6.407,"temperatureMin":50.07,"temperatureMinTime":1490882400,"temperatureMax":67.32,"temperatureMaxTime":1490914800,"apparentTemperatureMin":50.07,"apparentTemperatureMinTime":1490882400,"apparentTemperatureMax":67.32,"apparentTemperatureMaxTime":1490914800},"2018":{"time":1522393200,"summary":"Partly cloudy throughout the day.","icon":"clear-day","sunriseTime":1522418401,"sunsetTime":1522463639,"moonPhase":0.49,"precipIntensity":0,"precipIntensityMax":0,"precipProbability":0,"temperatureHigh":81.26,"temperatureHighTime":1522450800,"temperatureLow":46.15,"temperatureLowTime":1522504800,"apparentTemperatureHigh":81.26,"apparentTemperatureHighTime":1522450800,"apparentTemperatureLow":46.15,"apparentTemperatureLowTime":1522504800,"dewPoint":47.01,"humidity":0.6,"pressure":1016.61,"windSpeed":1.45,"windGust":8.79,"windGustTime":1522450800,"windBearing":204,"cloudCover":0.09,"uvIndex":7,"uvIndexTime":1522440000,"visibility":9.997,"temperatureMin":46.71,"temperatureMinTime":1522418400,"temperatureMax":81.26,"temperatureMaxTime":1522450800,"apparentTemperatureMin":46.71,"apparentTemperatureMinTime":1522418400,"apparentTemperatureMax":81.26,"apparentTemperatureMaxTime":1522450800},"2019":{"time":1553929200,"summary":"Clear throughout the day.","icon":"clear-day","sunriseTime":1553954424,"sunsetTime":1553999625,"moonPhase":0.84,"precipIntensity":0,"precipIntensityMax":0,"precipProbability":0,"temperatureHigh":68.79,"temperatureHighTime":1553990400,"temperatureLow":45.38,"temperatureLowTime":1554040800,"apparentTemperatureHigh":68.79,"apparentTemperatureHighTime":1553990400,"apparentTemperatureLow":45.38,"apparentTemperatureLowTime":1554040800,"dewPoint":38.43,"humidity":0.55,"pressure":1022.54,"windSpeed":3.79,"windGust":13.11,"windGustTime":1553986800,"windBearing":268,"cloudCover":0.02,"uvIndex":6,"uvIndexTime":1553979600,"visibility":9.956,"ozone":335.2,"temperatureMin":43.31,"temperatureMinTime":1553954400,"temperatureMax":68.79,"temperatureMaxTime":1553990400,"apparentTemperatureMin":43.31,"apparentTemperatureMinTime":1553954400,"apparentTemperatureMax":68.79,"apparentTemperatureMaxTime":1553990400}}